{
"meta":{"launch_mode":"Train","name":"experiment","iteration_count":1000,"learn_metrics":[{"best_value":"Min","name":"RMSE"}],"test_sets":[],"test_metrics":[],"learn_sets":["learn"]},
"iterations":[
{"learn":[0.6005021114],"iteration":0,"passed_time":0.000971765762,"remaining_time":0.9707939962},
{"learn":[0.5903734447],"iteration":1,"passed_time":0.003503497836,"remaining_time":1.74824542},
{"learn":[0.5802862163],"iteration":2,"passed_time":0.00435697602,"remaining_time":1.447968364},
{"learn":[0.5716064167],"iteration":3,"passed_time":0.005006595024,"remaining_time":1.246642161},
{"learn":[0.5632891783],"iteration":4,"passed_time":0.00574660268,"remaining_time":1.143573933},
{"learn":[0.5553495383],"iteration":5,"passed_time":0.006366920886,"remaining_time":1.05478656},
{"learn":[0.5471451358],"iteration":6,"passed_time":0.007011221345,"remaining_time":0.994591828},
{"learn":[0.5394987129],"iteration":7,"passed_time":0.008061388104,"remaining_time":0.9996121249},
{"learn":[0.5321817646],"iteration":8,"passed_time":0.008994265259,"remaining_time":0.9903685413},
{"learn":[0.5251201906],"iteration":9,"passed_time":0.009782292199,"remaining_time":0.9684469277},
{"learn":[0.5178606132],"iteration":10,"passed_time":0.01097011156,"remaining_time":0.9863127579},
{"learn":[0.5116679488],"iteration":11,"passed_time":0.01167907978,"remaining_time":0.9615775684},
{"learn":[0.5054400874],"iteration":12,"passed_time":0.01277624046,"remaining_time":0.970011487},
{"learn":[0.4990212177],"iteration":13,"passed_time":0.01380633739,"remaining_time":0.9723606193},
{"learn":[0.4934068582],"iteration":14,"passed_time":0.01482283842,"remaining_time":0.9733663896},
{"learn":[0.4878682684],"iteration":15,"passed_time":0.01593393101,"remaining_time":0.9799367572},
{"learn":[0.4817562746],"iteration":16,"passed_time":0.01710890092,"remaining_time":0.9892970357},
{"learn":[0.4762799099],"iteration":17,"passed_time":0.01801250814,"remaining_time":0.9826823886},
{"learn":[0.470882607],"iteration":18,"passed_time":0.01887513398,"remaining_time":0.97455297},
{"learn":[0.4657757569],"iteration":19,"passed_time":0.01971690148,"remaining_time":0.9661281727},
{"learn":[0.4609936734],"iteration":20,"passed_time":0.02086795511,"remaining_time":0.9728441929},
{"learn":[0.4564694441],"iteration":21,"passed_time":0.02184285791,"remaining_time":0.97101432},
{"learn":[0.4520538238],"iteration":22,"passed_time":0.02305918263,"remaining_time":0.9795139752},
{"learn":[0.4476551768],"iteration":23,"passed_time":0.0238768645,"remaining_time":0.9709924897},
{"learn":[0.4436679268],"iteration":24,"passed_time":0.02461842178,"remaining_time":0.9601184492},
{"learn":[0.4403930931],"iteration":25,"passed_time":0.02526728468,"remaining_time":0.9465513568},
{"learn":[0.4366805928],"iteration":26,"passed_time":0.02593879432,"remaining_time":0.9347572915},
{"learn":[0.4333822228],"iteration":27,"passed_time":0.02714206397,"remaining_time":0.9422173634},
{"learn":[0.4296099526],"iteration":28,"passed_time":0.02807563588,"remaining_time":0.9400497395},
{"learn":[0.4266334463],"iteration":29,"passed_time":0.02902702206,"remaining_time":0.9385403798},
{"learn":[0.4234766246],"iteration":30,"passed_time":0.03008424677,"remaining_time":0.9403753266},
{"learn":[0.4209525022],"iteration":31,"passed_time":0.03065243421,"remaining_time":0.9272361349},
{"learn":[0.4180612817],"iteration":32,"passed_time":0.03135041004,"remaining_time":0.9186620155},
{"learn":[0.4156005226],"iteration":33,"passed_time":0.03224334507,"remaining_time":0.9160903334},
{"learn":[0.4127153066],"iteration":34,"passed_time":0.03316416706,"remaining_time":0.9143834632},
{"learn":[0.4098541823],"iteration":35,"passed_time":0.03398305367,"remaining_time":0.9099906595},
{"learn":[0.4075270692],"iteration":36,"passed_time":0.03471191811,"remaining_time":0.9034480309},
{"learn":[0.4057695658],"iteration":37,"passed_time":0.03533025156,"remaining_time":0.8944132105},
{"learn":[0.4035225958],"iteration":38,"passed_time":0.03624152355,"remaining_time":0.893028311},
{"learn":[0.4014656046],"iteration":39,"passed_time":0.03710062619,"remaining_time":0.8904150285},
{"learn":[0.399106793],"iteration":40,"passed_time":0.03804322617,"remaining_time":0.8898403389},
{"learn":[0.3973837585],"iteration":41,"passed_time":0.03876919853,"remaining_time":0.8843069569},
{"learn":[0.3955768648],"iteration":42,"passed_time":0.03983887228,"remaining_time":0.8866465295},
{"learn":[0.3936997741],"iteration":43,"passed_time":0.04113127915,"remaining_time":0.8936705198},
{"learn":[0.3920148632],"iteration":44,"passed_time":0.04216039818,"remaining_time":0.8947373391},
{"learn":[0.3901911471],"iteration":45,"passed_time":0.04313438132,"remaining_time":0.8945695604},
{"learn":[0.3887503929],"iteration":46,"passed_time":0.04400557886,"remaining_time":0.892283333},
{"learn":[0.3868298428],"iteration":47,"passed_time":0.04500804767,"remaining_time":0.8926596122},
{"learn":[0.3851178635],"iteration":48,"passed_time":0.04597343558,"remaining_time":0.8922599436},
{"learn":[0.3840631768],"iteration":49,"passed_time":0.04687601396,"remaining_time":0.8906442652},
{"learn":[0.3829765004],"iteration":50,"passed_time":0.04781796393,"remaining_time":0.8897891719},
{"learn":[0.3817238181],"iteration":51,"passed_time":0.04858030392,"remaining_time":0.8856563099},
{"learn":[0.3803193085],"iteration":52,"passed_time":0.0495589309,"remaining_time":0.885515237},
{"learn":[0.3788911679],"iteration":53,"passed_time":0.05075279945,"remaining_time":0.889113857},
{"learn":[0.3781384806],"iteration":54,"passed_time":0.05132204003,"remaining_time":0.8818059604},
{"learn":[0.3766321565],"iteration":55,"passed_time":0.05256070711,"remaining_time":0.8860233484},
{"learn":[0.375740167],"iteration":56,"passed_time":0.05353970404,"remaining_time":0.8857533493},
{"learn":[0.3746788252],"iteration":57,"passed_time":0.05448519996,"remaining_time":0.8849147993},
{"learn":[0.3733512123],"iteration":58,"passed_time":0.05541238438,"remaining_time":0.8837805712},
{"learn":[0.3725161278],"iteration":59,"passed_time":0.05632269735,"remaining_time":0.8823889252},
{"learn":[0.3714751538],"iteration":60,"passed_time":0.05735955907,"remaining_time":0.8829610814},
{"learn":[0.3705561427],"iteration":61,"passed_time":0.05822565023,"remaining_time":0.8808977406},
{"learn":[0.3694169291],"iteration":62,"passed_time":0.05915036536,"remaining_time":0.879744323},
{"learn":[0.3684129967],"iteration":63,"passed_time":0.0601074111,"remaining_time":0.8790708873},
{"learn":[0.3675980724],"iteration":64,"passed_time":0.06124590035,"remaining_time":0.8809987204},
{"learn":[0.3666850518],"iteration":65,"passed_time":0.06211589931,"remaining_time":0.8790340903},
{"learn":[0.3660185919],"iteration":66,"passed_time":0.06416815221,"remaining_time":0.8935654629},
{"learn":[0.3653005236],"iteration":67,"passed_time":0.06574614687,"remaining_time":0.9011089542},
{"learn":[0.3643009505],"iteration":68,"passed_time":0.06681775562,"remaining_time":0.9015555143},
{"learn":[0.3637313202],"iteration":69,"passed_time":0.06776697264,"remaining_time":0.9003326364},
{"learn":[0.363187647],"iteration":70,"passed_time":0.0685852347,"remaining_time":0.8974039864},
{"learn":[0.3628683829],"iteration":71,"passed_time":0.06915267799,"remaining_time":0.891301183},
{"learn":[0.3619518389],"iteration":72,"passed_time":0.06997674775,"remaining_time":0.8886088378},
{"learn":[0.361578745],"iteration":73,"passed_time":0.07075802958,"remaining_time":0.8854315594},
{"learn":[0.3609777555],"iteration":74,"passed_time":0.07139671214,"remaining_time":0.8805594498},
{"learn":[0.3607265246],"iteration":75,"passed_time":0.07198609275,"remaining_time":0.8751993382},
{"learn":[0.3599946745],"iteration":76,"passed_time":0.07297733464,"remaining_time":0.8747802581},
{"learn":[0.3595119247],"iteration":77,"passed_time":0.07379671696,"remaining_time":0.872315039},
{"learn":[0.358989004],"iteration":78,"passed_time":0.074479224,"remaining_time":0.8682957633},
{"learn":[0.3587828782],"iteration":79,"passed_time":0.07501730207,"remaining_time":0.8626989738},
{"learn":[0.3585501624],"iteration":80,"passed_time":0.07574499726,"remaining_time":0.8593784257},
{"learn":[0.3582571611],"iteration":81,"passed_time":0.07638724467,"remaining_time":0.8551645197},
{"learn":[0.3580683368],"iteration":82,"passed_time":0.07691484382,"remaining_time":0.8497700215},
{"learn":[0.357890456],"iteration":83,"passed_time":0.07744280096,"remaining_time":0.8444953057},
{"learn":[0.3572507134],"iteration":84,"passed_time":0.07838109696,"remaining_time":0.8437494555},
{"learn":[0.3570186959],"iteration":85,"passed_time":0.07905775772,"remaining_time":0.8402184948},
{"learn":[0.3568603401],"iteration":86,"passed_time":0.07958886154,"remaining_time":0.835225639},
{"learn":[0.3564484061],"iteration":87,"passed_time":0.08042804134,"remaining_time":0.8335269739},
{"learn":[0.3562912029],"iteration":88,"passed_time":0.08100357143,"remaining_time":0.8291489166},
{"learn":[0.3558464182],"iteration":89,"passed_time":0.08176927067,"remaining_time":0.8267781812},
{"learn":[0.3554791859],"iteration":90,"passed_time":0.08267611793,"remaining_time":0.8258526505},
{"learn":[0.3552235253],"iteration":91,"passed_time":0.08334961811,"remaining_time":0.8226244918},
{"learn":[0.3549724567],"iteration":92,"passed_time":0.08414531985,"remaining_time":0.8206430656},
{"learn":[0.3544337717],"iteration":93,"passed_time":0.08496647631,"remaining_time":0.8189322078},
{"learn":[0.3540145061],"iteration":94,"passed_time":0.08591179979,"remaining_time":0.8184229349},
{"learn":[0.3535336073],"iteration":95,"passed_time":0.08677385045,"remaining_time":0.8171204251},
{"learn":[0.3530904837],"iteration":96,"passed_time":0.08752702736,"remaining_time":0.8148134609},
{"learn":[0.3530372361],"iteration":97,"passed_time":0.08807462689,"remaining_time":0.8106460557},
{"learn":[0.3526648282],"iteration":98,"passed_time":0.08897728166,"remaining_time":0.8097831391},
{"learn":[0.3525717355],"iteration":99,"passed_time":0.08955898592,"remaining_time":0.8060308733},
{"learn":[0.3523028139],"iteration":100,"passed_time":0.09027789916,"remaining_time":0.8035626866},
{"learn":[0.3521438434],"iteration":101,"passed_time":0.09119414559,"remaining_time":0.8028661053},
{"learn":[0.3518862564],"iteration":102,"passed_time":0.0920062628,"remaining_time":0.8012584246},
{"learn":[0.3517434467],"iteration":103,"passed_time":0.09265362199,"remaining_time":0.7982465895},
{"learn":[0.3513661171],"iteration":104,"passed_time":0.09337665327,"remaining_time":0.7959248065},
{"learn":[0.3511061621],"iteration":105,"passed_time":0.09418097571,"remaining_time":0.7943187951},
{"learn":[0.3507555613],"iteration":106,"passed_time":0.09499638041,"remaining_time":0.7928202589},
{"learn":[0.350360462],"iteration":107,"passed_time":0.09594577102,"remaining_time":0.7924409976},
{"learn":[0.3499553674],"iteration":108,"passed_time":0.09704812795,"remaining_time":0.7933016698},
{"learn":[0.3495851693],"iteration":109,"passed_time":0.09785334999,"remaining_time":0.791722559},
{"learn":[0.3494206319],"iteration":110,"passed_time":0.09858883455,"remaining_time":0.7895988641},
{"learn":[0.349114881],"iteration":111,"passed_time":0.1001126851,"remaining_time":0.793750575},
{"learn":[0.3488450839],"iteration":112,"passed_time":0.1019005974,"remaining_time":0.799874601},
{"learn":[0.3487564894],"iteration":113,"passed_time":0.1030235546,"remaining_time":0.8006918367},
{"learn":[0.3484783405],"iteration":114,"passed_time":0.1037870777,"remaining_time":0.7987092504},
{"learn":[0.3483615469],"iteration":115,"passed_time":0.1044402134,"remaining_time":0.7959064537},
{"learn":[0.3480473382],"iteration":116,"passed_time":0.1053314314,"remaining_time":0.7949372128},
{"learn":[0.3477435567],"iteration":117,"passed_time":0.1061625518,"remaining_time":0.7935200902},
{"learn":[0.3474316519],"iteration":118,"passed_time":0.1070159871,"remaining_time":0.7922780222},
{"learn":[0.3474170778],"iteration":119,"passed_time":0.1076715782,"remaining_time":0.7895915731},
{"learn":[0.3471492973],"iteration":120,"passed_time":0.1085798122,"remaining_time":0.7887740079},
{"learn":[0.3468790786],"iteration":121,"passed_time":0.1094292665,"remaining_time":0.7875319343},
{"learn":[0.3467993723],"iteration":122,"passed_time":0.1102738015,"remaining_time":0.78626117},
{"learn":[0.3466235021],"iteration":123,"passed_time":0.110870853,"remaining_time":0.7832489295},
{"learn":[0.346464541],"iteration":124,"passed_time":0.1117557965,"remaining_time":0.7822905758},
{"learn":[0.3462503261],"iteration":125,"passed_time":0.1126300995,"remaining_time":0.7812595791},
{"learn":[0.346201217],"iteration":126,"passed_time":0.1132006509,"remaining_time":0.778143057},
{"learn":[0.3461545328],"iteration":127,"passed_time":0.1138006917,"remaining_time":0.7752672125},
{"learn":[0.3458470171],"iteration":128,"passed_time":0.1147030198,"remaining_time":0.7744676761},
{"learn":[0.3457320537],"iteration":129,"passed_time":0.1157224854,"remaining_time":0.7744504792},
{"learn":[0.3456582769],"iteration":130,"passed_time":0.1164928003,"remaining_time":0.7727652173},
{"learn":[0.3455177393],"iteration":131,"passed_time":0.1173277942,"remaining_time":0.7715191314},
{"learn":[0.3453468222],"iteration":132,"passed_time":0.1181973237,"remaining_time":0.770504358},
{"learn":[0.3451605761],"iteration":133,"passed_time":0.1190413618,"remaining_time":0.7693270097},
{"learn":[0.345092636],"iteration":134,"passed_time":0.1196246747,"remaining_time":0.7664840267},
{"learn":[0.3449282435],"iteration":135,"passed_time":0.120694951,"remaining_time":0.766767924},
{"learn":[0.3448648946],"iteration":136,"passed_time":0.1213524728,"remaining_time":0.7644320001},
{"learn":[0.3448344207],"iteration":137,"passed_time":0.1219300791,"remaining_time":0.7616212186},
{"learn":[0.3448083153],"iteration":138,"passed_time":0.1224132423,"remaining_time":0.7582575657},
{"learn":[0.3445791016],"iteration":139,"passed_time":0.1232277786,"remaining_time":0.7569706403},
{"learn":[0.3443589804],"iteration":140,"passed_time":0.124373317,"remaining_time":0.7577069453},
{"learn":[0.3442399289],"iteration":141,"passed_time":0.1250319714,"remaining_time":0.7554748694},
{"learn":[0.3439638822],"iteration":142,"passed_time":0.1258852035,"remaining_time":0.7544309046},
{"learn":[0.3438353272],"iteration":143,"passed_time":0.1267017554,"remaining_time":0.7531715461},
{"learn":[0.3436907709],"iteration":144,"passed_time":0.1275777731,"remaining_time":0.7522689379},
{"learn":[0.3436783478],"iteration":145,"passed_time":0.1280851531,"remaining_time":0.7492104162},
{"learn":[0.343495869],"iteration":146,"passed_time":0.1289687326,"remaining_time":0.7483695842},
{"learn":[0.3434843953],"iteration":147,"passed_time":0.129474921,"remaining_time":0.7453556261},
{"learn":[0.3433380217],"iteration":148,"passed_time":0.1305342192,"remaining_time":0.7455343659},
{"learn":[0.3431190332],"iteration":149,"passed_time":0.1314017172,"remaining_time":0.744609731},
{"learn":[0.3428550279],"iteration":150,"passed_time":0.1322937287,"remaining_time":0.7438236801},
{"learn":[0.3428209836],"iteration":151,"passed_time":0.1329481659,"remaining_time":0.7417108205},
{"learn":[0.3427377087],"iteration":152,"passed_time":0.1336821005,"remaining_time":0.7400571184},
{"learn":[0.3426214856],"iteration":153,"passed_time":0.1346448363,"remaining_time":0.7396722823},
{"learn":[0.3425089834],"iteration":154,"passed_time":0.1355054276,"remaining_time":0.7387231374},
{"learn":[0.3423851518],"iteration":155,"passed_time":0.1364099174,"remaining_time":0.7380126302},
{"learn":[0.342343117],"iteration":156,"passed_time":0.137179256,"remaining_time":0.7365739668},
{"learn":[0.3421583002],"iteration":157,"passed_time":0.1382549774,"remaining_time":0.7367765249},
{"learn":[0.3421509385],"iteration":158,"passed_time":0.1387527063,"remaining_time":0.733905824},
{"learn":[0.3420500932],"iteration":159,"passed_time":0.1396217216,"remaining_time":0.7330140383},
{"learn":[0.3420270402],"iteration":160,"passed_time":0.1401970769,"remaining_time":0.7305922207},
{"learn":[0.341867622],"iteration":161,"passed_time":0.1412404689,"remaining_time":0.7306142772},
{"learn":[0.3418053893],"iteration":162,"passed_time":0.1421012214,"remaining_time":0.7296854131},
{"learn":[0.341691782],"iteration":163,"passed_time":0.1429369895,"remaining_time":0.7286300197},
{"learn":[0.3415501149],"iteration":164,"passed_time":0.1437352713,"remaining_time":0.7273875848},
{"learn":[0.3414470239],"iteration":165,"passed_time":0.1445917464,"remaining_time":0.7264428707},
{"learn":[0.3414118412],"iteration":166,"passed_time":0.1452756588,"remaining_time":0.7246384659},
{"learn":[0.3413226046],"iteration":167,"passed_time":0.1461704397,"remaining_time":0.7238917015},
{"learn":[0.3413156973],"iteration":168,"passed_time":0.1469108347,"remaining_time":0.7223840452},
{"learn":[0.3412653589],"iteration":169,"passed_time":0.1476664952,"remaining_time":0.720959947},
{"learn":[0.3411622574],"iteration":170,"passed_time":0.148521523,"remaining_time":0.720025395},
{"learn":[0.3411092853],"iteration":171,"passed_time":0.1494411298,"remaining_time":0.7194026481},
{"learn":[0.3409970887],"iteration":172,"passed_time":0.1503508599,"remaining_time":0.718729255},
{"learn":[0.340943059],"iteration":173,"passed_time":0.1513829377,"remaining_time":0.7186339457},
{"learn":[0.3407933428],"iteration":174,"passed_time":0.1522545658,"remaining_time":0.7177715244},
{"learn":[0.3407793717],"iteration":175,"passed_time":0.1528353673,"remaining_time":0.7155474017},
{"learn":[0.3407443435],"iteration":176,"passed_time":0.1536080092,"remaining_time":0.7142338507},
{"learn":[0.3406805156],"iteration":177,"passed_time":0.1545227095,"remaining_time":0.7135824},
{"learn":[0.3405451809],"iteration":178,"passed_time":0.1553697084,"remaining_time":0.7126174891},
{"learn":[0.3404339772],"iteration":179,"passed_time":0.1562437258,"remaining_time":0.7117769732},
{"learn":[0.3403681271],"iteration":180,"passed_time":0.1571097703,"remaining_time":0.7109000104},
{"learn":[0.3402173795],"iteration":181,"passed_time":0.1579380098,"remaining_time":0.7098532529},
{"learn":[0.3401556827],"iteration":182,"passed_time":0.1586742393,"remaining_time":0.7083981065},
{"learn":[0.3401386287],"iteration":183,"passed_time":0.1592476504,"remaining_time":0.7062287103},
{"learn":[0.3400778641],"iteration":184,"passed_time":0.1601967725,"remaining_time":0.7057317274},
{"learn":[0.3400703084],"iteration":185,"passed_time":0.1608576192,"remaining_time":0.7039682904},
{"learn":[0.3399854869],"iteration":186,"passed_time":0.1617635016,"remaining_time":0.7032819617},
{"learn":[0.3399790644],"iteration":187,"passed_time":0.1623294709,"remaining_time":0.7011251617},
{"learn":[0.33991692],"iteration":188,"passed_time":0.1630099577,"remaining_time":0.699476591},
{"learn":[0.3398938782],"iteration":189,"passed_time":0.1636434714,"remaining_time":0.697637957},
{"learn":[0.3398143958],"iteration":190,"passed_time":0.164489426,"remaining_time":0.6967117573},
{"learn":[0.3398030117],"iteration":191,"passed_time":0.1653489711,"remaining_time":0.6958435868},
{"learn":[0.3397266532],"iteration":192,"passed_time":0.166072973,"remaining_time":0.6944087523},
{"learn":[0.3397258785],"iteration":193,"passed_time":0.1666715981,"remaining_time":0.6924603508},
{"learn":[0.3396787043],"iteration":194,"passed_time":0.1673910803,"remaining_time":0.6910247162},
{"learn":[0.3396722452],"iteration":195,"passed_time":0.1679940159,"remaining_time":0.6891183103},
{"learn":[0.3396588632],"iteration":196,"passed_time":0.1694124948,"remaining_time":0.6905494076},
{"learn":[0.3395394675],"iteration":197,"passed_time":0.1710304759,"remaining_time":0.6927598065},
{"learn":[0.3394985295],"iteration":198,"passed_time":0.1720267177,"remaining_time":0.6924291502},
{"learn":[0.3393423072],"iteration":199,"passed_time":0.1731249562,"remaining_time":0.6924998249},
{"learn":[0.3391656419],"iteration":200,"passed_time":0.1748978395,"remaining_time":0.6952406654},
{"learn":[0.3390405278],"iteration":201,"passed_time":0.1758205112,"remaining_time":0.6945780591},
{"learn":[0.3390191298],"iteration":202,"passed_time":0.1768658991,"remaining_time":0.6943946876},
{"learn":[0.3389926003],"iteration":203,"passed_time":0.1784176266,"remaining_time":0.6961785824},
{"learn":[0.3388226723],"iteration":204,"passed_time":0.1801498433,"remaining_time":0.6986298801},
{"learn":[0.3386829321],"iteration":205,"passed_time":0.1817333887,"remaining_time":0.7004675275},
{"learn":[0.3386565483],"iteration":206,"passed_time":0.1828218118,"remaining_time":0.7003753468},
{"learn":[0.3386361908],"iteration":207,"passed_time":0.1837456648,"remaining_time":0.6996469544},
{"learn":[0.3384672444],"iteration":208,"passed_time":0.1862166589,"remaining_time":0.7047721396},
{"learn":[0.3384656936],"iteration":209,"passed_time":0.1874033314,"remaining_time":0.7049934847},
{"learn":[0.338395115],"iteration":210,"passed_time":0.188371064,"remaining_time":0.7043827937},
{"learn":[0.3383732516],"iteration":211,"passed_time":0.1897644927,"remaining_time":0.705351039},
{"learn":[0.3383438963],"iteration":212,"passed_time":0.1910470603,"remaining_time":0.705887495},
{"learn":[0.3383354417],"iteration":213,"passed_time":0.192138502,"remaining_time":0.7057049652},
{"learn":[0.3382972989],"iteration":214,"passed_time":0.1931475732,"remaining_time":0.7052132323},
{"learn":[0.3382197784],"iteration":215,"passed_time":0.1944784682,"remaining_time":0.7058848106},
{"learn":[0.3380509241],"iteration":216,"passed_time":0.1965332236,"remaining_time":0.7091498344},
{"learn":[0.3380337731],"iteration":217,"passed_time":0.1978770121,"remaining_time":0.7098157039},
{"learn":[0.3379973517],"iteration":218,"passed_time":0.1988554932,"remaining_time":0.7091604577},
{"learn":[0.337912929],"iteration":219,"passed_time":0.2000484645,"remaining_time":0.7092627378},
{"learn":[0.3378400531],"iteration":220,"passed_time":0.2010713334,"remaining_time":0.7087537045},
{"learn":[0.3378327322],"iteration":221,"passed_time":0.2017395841,"remaining_time":0.7069972811},
{"learn":[0.3377991353],"iteration":222,"passed_time":0.2026641418,"remaining_time":0.706143669},
{"learn":[0.3377920268],"iteration":223,"passed_time":0.2036063942,"remaining_time":0.7053507228},
{"learn":[0.33776303],"iteration":224,"passed_time":0.2042593169,"remaining_time":0.7035598693},
{"learn":[0.3377136708],"iteration":225,"passed_time":0.2051789415,"remaining_time":0.702692481},
{"learn":[0.3376076075],"iteration":226,"passed_time":0.2060270749,"remaining_time":0.7015811845},
{"learn":[0.3375212498],"iteration":227,"passed_time":0.2069185533,"remaining_time":0.700618961},
{"learn":[0.3374323503],"iteration":228,"passed_time":0.208035567,"remaining_time":0.7004166905},
{"learn":[0.3374210958],"iteration":229,"passed_time":0.2091438184,"remaining_time":0.7001771311},
{"learn":[0.3373668709],"iteration":230,"passed_time":0.2102558542,"remaining_time":0.6999426487},
{"learn":[0.337360431],"iteration":231,"passed_time":0.2112627848,"remaining_time":0.6993526668},
{"learn":[0.3372093322],"iteration":232,"passed_time":0.2126128643,"remaining_time":0.6998886992},
{"learn":[0.3371489868],"iteration":233,"passed_time":0.2138852423,"remaining_time":0.7001542545},
{"learn":[0.33712544],"iteration":234,"passed_time":0.2151871791,"remaining_time":0.7005029446},
{"learn":[0.3370951645],"iteration":235,"passed_time":0.216269364,"remaining_time":0.700126246},
{"learn":[0.3370545885],"iteration":236,"passed_time":0.2175576933,"remaining_time":0.7004072573},
{"learn":[0.3370237216],"iteration":237,"passed_time":0.2189695493,"remaining_time":0.7010705738},
{"learn":[0.337023527],"iteration":238,"passed_time":0.219776449,"remaining_time":0.6997902833},
{"learn":[0.3370215991],"iteration":239,"passed_time":0.2206561488,"remaining_time":0.6987444713},
{"learn":[0.3369119404],"iteration":240,"passed_time":0.2223736566,"remaining_time":0.7003386116},
{"learn":[0.3369117572],"iteration":241,"passed_time":0.2231443461,"remaining_time":0.6989397288},
{"learn":[0.3367389738],"iteration":242,"passed_time":0.2246831197,"remaining_time":0.699938772},
{"learn":[0.3366367835],"iteration":243,"passed_time":0.226449389,"remaining_time":0.7016218773},
{"learn":[0.3365818352],"iteration":244,"passed_time":0.227370878,"remaining_time":0.7006735219},
{"learn":[0.3365802135],"iteration":245,"passed_time":0.2286217325,"remaining_time":0.7007349038},
{"learn":[0.3364659074],"iteration":246,"passed_time":0.2302134477,"remaining_time":0.7018248021},
{"learn":[0.336413888],"iteration":247,"passed_time":0.2325244195,"remaining_time":0.7050740461},
{"learn":[0.3364069749],"iteration":248,"passed_time":0.2338544847,"remaining_time":0.7053201527},
{"learn":[0.3363162192],"iteration":249,"passed_time":0.2359209947,"remaining_time":0.7077629842},
{"learn":[0.3363106283],"iteration":250,"passed_time":0.2372998346,"remaining_time":0.7081178332},
{"learn":[0.3363093737],"iteration":251,"passed_time":0.2384096245,"remaining_time":0.707660314},
{"learn":[0.3361913367],"iteration":252,"passed_time":0.2400533752,"remaining_time":0.7087741946},
{"learn":[0.3361472487],"iteration":253,"passed_time":0.2406971571,"remaining_time":0.7069294458},
{"learn":[0.3361429715],"iteration":254,"passed_time":0.2412927964,"remaining_time":0.704953464},
{"learn":[0.336034043],"iteration":255,"passed_time":0.2422121421,"remaining_time":0.7039290379},
{"learn":[0.3359918277],"iteration":256,"passed_time":0.24296787,"remaining_time":0.7024324025},
{"learn":[0.3359757771],"iteration":257,"passed_time":0.2435461946,"remaining_time":0.7004313039},
{"learn":[0.3359671329],"iteration":258,"passed_time":0.2441091002,"remaining_time":0.6983970781},
{"learn":[0.335965991],"iteration":259,"passed_time":0.2446816853,"remaining_time":0.6964017198},
{"learn":[0.335917473],"iteration":260,"passed_time":0.2456746373,"remaining_time":0.695607498},
{"learn":[0.3357609942],"iteration":261,"passed_time":0.2468338009,"remaining_time":0.6952799429},
{"learn":[0.3357024006],"iteration":262,"passed_time":0.2479527122,"remaining_time":0.6948332656},
{"learn":[0.335699561],"iteration":263,"passed_time":0.2485418409,"remaining_time":0.692904526},
{"learn":[0.3356391883],"iteration":264,"passed_time":0.2495788079,"remaining_time":0.6922280143},
{"learn":[0.3356076802],"iteration":265,"passed_time":0.2506100228,"remaining_time":0.69153292},
{"learn":[0.3355890262],"iteration":266,"passed_time":0.2514430326,"remaining_time":0.690291172},
{"learn":[0.3355202814],"iteration":267,"passed_time":0.2523222688,"remaining_time":0.6891787341},
{"learn":[0.3355144931],"iteration":268,"passed_time":0.2529769721,"remaining_time":0.6874578685},
{"learn":[0.3354572961],"iteration":269,"passed_time":0.2538254952,"remaining_time":0.6862689314},
{"learn":[0.3354540724],"iteration":270,"passed_time":0.2543619661,"remaining_time":0.684243075},
{"learn":[0.335389152],"iteration":271,"passed_time":0.2553568971,"remaining_time":0.6834552246},
{"learn":[0.3352982065],"iteration":272,"passed_time":0.2562158632,"remaining_time":0.6823037822},
{"learn":[0.3352521638],"iteration":273,"passed_time":0.2570853286,"remaining_time":0.6811822941},
{"learn":[0.3351697046],"iteration":274,"passed_time":0.2579307548,"remaining_time":0.6799992625},
{"learn":[0.3351497909],"iteration":275,"passed_time":0.2587832608,"remaining_time":0.6788372494},
{"learn":[0.3351476679],"iteration":276,"passed_time":0.2593092259,"remaining_time":0.6768251635},
{"learn":[0.3351447613],"iteration":277,"passed_time":0.2599307376,"remaining_time":0.6750719157},
{"learn":[0.3350601483],"iteration":278,"passed_time":0.260887229,"remaining_time":0.6741924448},
{"learn":[0.3350594766],"iteration":279,"passed_time":0.2614876471,"remaining_time":0.6723968069},
{"learn":[0.3350530468],"iteration":280,"passed_time":0.262560954,"remaining_time":0.6718196652},
{"learn":[0.3350112989],"iteration":281,"passed_time":0.2638814427,"remaining_time":0.671868354},
{"learn":[0.3348971896],"iteration":282,"passed_time":0.2648306817,"remaining_time":0.6709667801},
{"learn":[0.3348218907],"iteration":283,"passed_time":0.2656951248,"remaining_time":0.6698510894},
{"learn":[0.3348171375],"iteration":284,"passed_time":0.2663636977,"remaining_time":0.6682457678},
{"learn":[0.3347265856],"iteration":285,"passed_time":0.2672210408,"remaining_time":0.6671182627},
{"learn":[0.3347229988],"iteration":286,"passed_time":0.2679471613,"remaining_time":0.6656666412},
{"learn":[0.3346099633],"iteration":287,"passed_time":0.268809362,"remaining_time":0.6645564784},
{"learn":[0.3346030138],"iteration":288,"passed_time":0.2695153911,"remaining_time":0.6630638169},
{"learn":[0.3345537808],"iteration":289,"passed_time":0.270370545,"remaining_time":0.6619416793},
{"learn":[0.334477074],"iteration":290,"passed_time":0.2712699918,"remaining_time":0.6609292927},
{"learn":[0.3343707522],"iteration":291,"passed_time":0.2721249054,"remaining_time":0.6598097021},
{"learn":[0.3343428628],"iteration":292,"passed_time":0.2732422925,"remaining_time":0.6593252588},
{"learn":[0.3342548009],"iteration":293,"passed_time":0.2743065243,"remaining_time":0.6587088644},
{"learn":[0.3342313088],"iteration":294,"passed_time":0.2750476487,"remaining_time":0.6573172622},
{"learn":[0.3342146168],"iteration":295,"passed_time":0.2762605289,"remaining_time":0.6570520688},
{"learn":[0.3341943997],"iteration":296,"passed_time":0.2770843572,"remaining_time":0.6558596065},
{"learn":[0.3341369054],"iteration":297,"passed_time":0.2779217617,"remaining_time":0.6547015998},
{"learn":[0.3341350149],"iteration":298,"passed_time":0.278428121,"remaining_time":0.6527696081},
{"learn":[0.3341235888],"iteration":299,"passed_time":0.2792637174,"remaining_time":0.6516153407},
{"learn":[0.3340678677],"iteration":300,"passed_time":0.2801291744,"remaining_time":0.6505325346},
{"learn":[0.3339947461],"iteration":301,"passed_time":0.2810239688,"remaining_time":0.6495189743},
{"learn":[0.3339593183],"iteration":302,"passed_time":0.2818383265,"remaining_time":0.648321167},
{"learn":[0.3339544104],"iteration":303,"passed_time":0.2825028943,"remaining_time":0.6467829423},
{"learn":[0.3339508645],"iteration":304,"passed_time":0.2831728019,"remaining_time":0.6452626142},
{"learn":[0.3339472415],"iteration":305,"passed_time":0.2838477159,"remaining_time":0.6437591988},
{"learn":[0.3339122234],"iteration":306,"passed_time":0.2848073544,"remaining_time":0.6429038977},
{"learn":[0.3338942138],"iteration":307,"passed_time":0.2856905419,"remaining_time":0.6418761525},
{"learn":[0.333828979],"iteration":308,"passed_time":0.2865504157,"remaining_time":0.6407972079},
{"learn":[0.3338240373],"iteration":309,"passed_time":0.287309067,"remaining_time":0.6394943749},
{"learn":[0.3338040596],"iteration":310,"passed_time":0.2881672133,"remaining_time":0.6384154661},
{"learn":[0.3337577486],"iteration":311,"passed_time":0.2892352209,"remaining_time":0.6378007436},
{"learn":[0.3337081428],"iteration":312,"passed_time":0.2900361803,"remaining_time":0.6365969835},
{"learn":[0.3337073434],"iteration":313,"passed_time":0.2906356756,"remaining_time":0.634955648},
{"learn":[0.3336145566],"iteration":314,"passed_time":0.2914844876,"remaining_time":0.6338630921},
{"learn":[0.333525223],"iteration":315,"passed_time":0.2923380912,"remaining_time":0.6327824505},
{"learn":[0.3334095031],"iteration":316,"passed_time":0.293175856,"remaining_time":0.6316691155},
{"learn":[0.3333622442],"iteration":317,"passed_time":0.2940810024,"remaining_time":0.630702024},
{"learn":[0.3333567726],"iteration":318,"passed_time":0.2948097885,"remaining_time":0.6293588275},
{"learn":[0.3333555343],"iteration":319,"passed_time":0.2952996371,"remaining_time":0.6275117288},
{"learn":[0.3332966574],"iteration":320,"passed_time":0.2961942498,"remaining_time":0.6265292698},
{"learn":[0.3331471034],"iteration":321,"passed_time":0.2970560771,"remaining_time":0.6254783238},
{"learn":[0.3331460396],"iteration":322,"passed_time":0.2975550212,"remaining_time":0.6236679547},
{"learn":[0.3330183134],"iteration":323,"passed_time":0.298500744,"remaining_time":0.6227978485},
{"learn":[0.3329888442],"iteration":324,"passed_time":0.2993836124,"remaining_time":0.6217967335},
{"learn":[0.3328742765],"iteration":325,"passed_time":0.3002283141,"remaining_time":0.6207174346},
{"learn":[0.3328626493],"iteration":326,"passed_time":0.3010631656,"remaining_time":0.619619298},
{"learn":[0.3328617138],"iteration":327,"passed_time":0.3015629885,"remaining_time":0.6178363666},
{"learn":[0.3328593483],"iteration":328,"passed_time":0.3023218003,"remaining_time":0.6165894467},
{"learn":[0.3328573014],"iteration":329,"passed_time":0.302990846,"remaining_time":0.6151632328},
{"learn":[0.3328165137],"iteration":330,"passed_time":0.3039141573,"remaining_time":0.6142555023},
{"learn":[0.3327599947],"iteration":331,"passed_time":0.3049071672,"remaining_time":0.6134879147},
{"learn":[0.3327320069],"iteration":332,"passed_time":0.305791088,"remaining_time":0.6125004676},
{"learn":[0.332715218],"iteration":333,"passed_time":0.3066383303,"remaining_time":0.611440503},
{"learn":[0.3327012212],"iteration":334,"passed_time":0.3074630841,"remaining_time":0.6103371668},
{"learn":[0.3326112729],"iteration":335,"passed_time":0.3082912124,"remaining_time":0.6092421579},
{"learn":[0.3325718185],"iteration":336,"passed_time":0.3091274296,"remaining_time":0.6081646463},
{"learn":[0.3325680549],"iteration":337,"passed_time":0.3096788501,"remaining_time":0.6065307656},
{"learn":[0.3325521415],"iteration":338,"passed_time":0.3105278476,"remaining_time":0.6054835023},
{"learn":[0.3325485154],"iteration":339,"passed_time":0.311098551,"remaining_time":0.6038971873},
{"learn":[0.3324806225],"iteration":340,"passed_time":0.3125848898,"remaining_time":0.6040863413},
{"learn":[0.3324541834],"iteration":341,"passed_time":0.3134563323,"remaining_time":0.603082651},
{"learn":[0.3323805339],"iteration":342,"passed_time":0.3142932002,"remaining_time":0.6020135059},
{"learn":[0.3323795439],"iteration":343,"passed_time":0.3148872586,"remaining_time":0.6004826792},
{"learn":[0.3323598528],"iteration":344,"passed_time":0.3159177073,"remaining_time":0.5997857922},
{"learn":[0.332329508],"iteration":345,"passed_time":0.3168895441,"remaining_time":0.5989761903},
{"learn":[0.3322850721],"iteration":346,"passed_time":0.3177430068,"remaining_time":0.5979428918},
{"learn":[0.332284387],"iteration":347,"passed_time":0.3183271842,"remaining_time":0.5964061038},
{"learn":[0.3322674933],"iteration":348,"passed_time":0.319190445,"remaining_time":0.5953953574},
{"learn":[0.3322101666],"iteration":349,"passed_time":0.3200449444,"remaining_time":0.5943691824},
{"learn":[0.3322067963],"iteration":350,"passed_time":0.320620638,"remaining_time":0.5928284731},
{"learn":[0.3322044631],"iteration":351,"passed_time":0.3211192681,"remaining_time":0.5911513799},
{"learn":[0.3321668183],"iteration":352,"passed_time":0.3219933257,"remaining_time":0.5901690701},
{"learn":[0.3321546372],"iteration":353,"passed_time":0.322853228,"remaining_time":0.5891615405},
{"learn":[0.3321470013],"iteration":354,"passed_time":0.3235582433,"remaining_time":0.587873428},
{"learn":[0.3321225326],"iteration":355,"passed_time":0.324430609,"remaining_time":0.5868913263},
{"learn":[0.3321203481],"iteration":356,"passed_time":0.3249511451,"remaining_time":0.5852761522},
{"learn":[0.332108846],"iteration":357,"passed_time":0.325809175,"remaining_time":0.5842723193},
{"learn":[0.3320833008],"iteration":358,"passed_time":0.3266649596,"remaining_time":0.58326529},
{"learn":[0.3320805248],"iteration":359,"passed_time":0.3272392017,"remaining_time":0.5817585807},
{"learn":[0.3320685446],"iteration":360,"passed_time":0.3280737908,"remaining_time":0.5807178735},
{"learn":[0.3319862446],"iteration":361,"passed_time":0.3291283395,"remaining_time":0.5800659685},
{"learn":[0.3319239094],"iteration":362,"passed_time":0.3299454057,"remaining_time":0.5789951059},
{"learn":[0.3318995974],"iteration":363,"passed_time":0.3308409851,"remaining_time":0.5780628202},
{"learn":[0.3318231478],"iteration":364,"passed_time":0.3316948271,"remaining_time":0.5770581239},
{"learn":[0.3317827237],"iteration":365,"passed_time":0.3326465539,"remaining_time":0.576223812},
{"learn":[0.3317808908],"iteration":366,"passed_time":0.3331614,"remaining_time":0.5746353303},
{"learn":[0.3317803627],"iteration":367,"passed_time":0.3347776225,"remaining_time":0.5749441778},
{"learn":[0.3316917779],"iteration":368,"passed_time":0.3368287158,"remaining_time":0.5759862321},
{"learn":[0.3316719367],"iteration":369,"passed_time":0.3382247257,"remaining_time":0.5758961546},
{"learn":[0.3316290938],"iteration":370,"passed_time":0.3390621719,"remaining_time":0.574852038},
{"learn":[0.3315748812],"iteration":371,"passed_time":0.3403259368,"remaining_time":0.5745287321},
{"learn":[0.3314544895],"iteration":372,"passed_time":0.3416599373,"remaining_time":0.5743184469},
{"learn":[0.3313385463],"iteration":373,"passed_time":0.3431970601,"remaining_time":0.5744421381},
{"learn":[0.33133573],"iteration":374,"passed_time":0.3439911887,"remaining_time":0.5733186479},
{"learn":[0.331265277],"iteration":375,"passed_time":0.3456190972,"remaining_time":0.5735806294},
{"learn":[0.331263407],"iteration":376,"passed_time":0.3468864517,"remaining_time":0.5732367623},
{"learn":[0.3312509114],"iteration":377,"passed_time":0.3484825283,"remaining_time":0.5734289223},
{"learn":[0.3312471752],"iteration":378,"passed_time":0.3497499615,"remaining_time":0.573073156},
{"learn":[0.3311579938],"iteration":379,"passed_time":0.3512901921,"remaining_time":0.5731576818},
{"learn":[0.3311204394],"iteration":380,"passed_time":0.3526825681,"remaining_time":0.5729934637},
{"learn":[0.3311202479],"iteration":381,"passed_time":0.353209221,"remaining_time":0.5714222475},
{"learn":[0.3311199183],"iteration":382,"passed_time":0.3538474271,"remaining_time":0.5700361946},
{"learn":[0.3311186042],"iteration":383,"passed_time":0.3545705807,"remaining_time":0.5687903065},
{"learn":[0.3311050195],"iteration":384,"passed_time":0.3557521661,"remaining_time":0.5682794341},
{"learn":[0.3311033572],"iteration":385,"passed_time":0.3570418618,"remaining_time":0.5679370548},
{"learn":[0.3310743964],"iteration":386,"passed_time":0.358470757,"remaining_time":0.5678102689},
{"learn":[0.3310296858],"iteration":387,"passed_time":0.3592935673,"remaining_time":0.5667207814},
{"learn":[0.3310280959],"iteration":388,"passed_time":0.3597845724,"remaining_time":0.5651115005},
{"learn":[0.3310184906],"iteration":389,"passed_time":0.360653034,"remaining_time":0.5640983353},
{"learn":[0.3310180682],"iteration":390,"passed_time":0.3613548027,"remaining_time":0.5628262784},
{"learn":[0.3309894015],"iteration":391,"passed_time":0.3622625797,"remaining_time":0.5618766542},
{"learn":[0.3308880824],"iteration":392,"passed_time":0.3630846589,"remaining_time":0.5607948803},
{"learn":[0.3308866992],"iteration":393,"passed_time":0.3635663485,"remaining_time":0.5591908812},
{"learn":[0.3308535427],"iteration":394,"passed_time":0.3644385652,"remaining_time":0.5581907138},
{"learn":[0.3308519883],"iteration":395,"passed_time":0.3650339892,"remaining_time":0.5567690139},
{"learn":[0.3308500037],"iteration":396,"passed_time":0.3656118378,"remaining_time":0.5553247813},
{"learn":[0.3308369903],"iteration":397,"passed_time":0.3664982248,"remaining_time":0.5543515863},
{"learn":[0.3308367633],"iteration":398,"passed_time":0.3671696218,"remaining_time":0.5530549943},
{"learn":[0.3308360334],"iteration":399,"passed_time":0.3677568838,"remaining_time":0.5516353257},
{"learn":[0.3308033785],"iteration":400,"passed_time":0.3686420699,"remaining_time":0.5506648377},
{"learn":[0.3308031426],"iteration":401,"passed_time":0.3694765303,"remaining_time":0.5496193162},
{"learn":[0.3307576791],"iteration":402,"passed_time":0.3705253199,"remaining_time":0.5488923473},
{"learn":[0.3307122933],"iteration":403,"passed_time":0.3714650837,"remaining_time":0.5480029453},
{"learn":[0.3307005102],"iteration":404,"passed_time":0.3723350811,"remaining_time":0.5470107982},
{"learn":[0.3306568767],"iteration":405,"passed_time":0.3731915343,"remaining_time":0.5459994369},
{"learn":[0.3305792904],"iteration":406,"passed_time":0.3740471076,"remaining_time":0.5449875548},
{"learn":[0.3305603997],"iteration":407,"passed_time":0.3749065636,"remaining_time":0.5439820727},
{"learn":[0.3305601736],"iteration":408,"passed_time":0.3754850305,"remaining_time":0.5425712788},
{"learn":[0.3305585142],"iteration":409,"passed_time":0.3760655817,"remaining_time":0.5411675445},
{"learn":[0.3305239821],"iteration":410,"passed_time":0.3769685887,"remaining_time":0.540229924},
{"learn":[0.3305230104],"iteration":411,"passed_time":0.3774842696,"remaining_time":0.5387396858},
{"learn":[0.3304050809],"iteration":412,"passed_time":0.3784717839,"remaining_time":0.5379247873},
{"learn":[0.3303229048],"iteration":413,"passed_time":0.3793573597,"remaining_time":0.5369647651},
{"learn":[0.3303219537],"iteration":414,"passed_time":0.3799491868,"remaining_time":0.5355910223},
{"learn":[0.3303210485],"iteration":415,"passed_time":0.3804072722,"remaining_time":0.534033286},
{"learn":[0.3302496169],"iteration":416,"passed_time":0.3812908852,"remaining_time":0.533075746},
{"learn":[0.3302271788],"iteration":417,"passed_time":0.3823490396,"remaining_time":0.5323615815},
{"learn":[0.3301620353],"iteration":418,"passed_time":0.3832611302,"remaining_time":0.5314432378},
{"learn":[0.3301600615],"iteration":419,"passed_time":0.3840138947,"remaining_time":0.5303049022},
{"learn":[0.330129315],"iteration":420,"passed_time":0.3849097805,"remaining_time":0.5293652325},
{"learn":[0.3301028911],"iteration":421,"passed_time":0.3857503112,"remaining_time":0.5283499523},
{"learn":[0.3300277243],"iteration":422,"passed_time":0.3865830943,"remaining_time":0.52732493},
{"learn":[0.3300268124],"iteration":423,"passed_time":0.3871096592,"remaining_time":0.52588482},
{"learn":[0.3298925592],"iteration":424,"passed_time":0.387994828,"remaining_time":0.524934179},
{"learn":[0.3298467493],"iteration":425,"passed_time":0.3889602807,"remaining_time":0.5240920214},
{"learn":[0.3298282222],"iteration":426,"passed_time":0.3897965016,"remaining_time":0.5230758676},
{"learn":[0.3298279905],"iteration":427,"passed_time":0.3903166613,"remaining_time":0.5216381548},
{"learn":[0.3297953673],"iteration":428,"passed_time":0.3911671672,"remaining_time":0.5206444113},
{"learn":[0.3297743642],"iteration":429,"passed_time":0.3920680301,"remaining_time":0.5197180864},
{"learn":[0.3297724582],"iteration":430,"passed_time":0.3926528255,"remaining_time":0.5183746118},
{"learn":[0.3296747824],"iteration":431,"passed_time":0.3935751531,"remaining_time":0.517478442},
{"learn":[0.3296455654],"iteration":432,"passed_time":0.394397522,"remaining_time":0.5164512586},
{"learn":[0.3295879878],"iteration":433,"passed_time":0.3952147981,"remaining_time":0.5154183772},
{"learn":[0.3295091164],"iteration":434,"passed_time":0.3960211824,"remaining_time":0.5143723404},
{"learn":[0.329497797],"iteration":435,"passed_time":0.3968516462,"remaining_time":0.5133585515},
{"learn":[0.3294604604],"iteration":436,"passed_time":0.3977554679,"remaining_time":0.5124401109},
{"learn":[0.3294150599],"iteration":437,"passed_time":0.3985440253,"remaining_time":0.5113738407},
{"learn":[0.3293679085],"iteration":438,"passed_time":0.399409029,"remaining_time":0.5104065268},
{"learn":[0.3293669901],"iteration":439,"passed_time":0.399885186,"remaining_time":0.5089447821},
{"learn":[0.3293035398],"iteration":440,"passed_time":0.4007323036,"remaining_time":0.5079577273},
{"learn":[0.3292264517],"iteration":441,"passed_time":0.4015816163,"remaining_time":0.5069740767},
{"learn":[0.3292248727],"iteration":442,"passed_time":0.4021735646,"remaining_time":0.505667439},
{"learn":[0.3291717306],"iteration":443,"passed_time":0.4030689782,"remaining_time":0.5047440357},
{"learn":[0.3291364062],"iteration":444,"passed_time":0.4039539583,"remaining_time":0.5038077458},
{"learn":[0.3291359179],"iteration":445,"passed_time":0.4048276903,"remaining_time":0.502857714},
{"learn":[0.329133761],"iteration":446,"passed_time":0.4054905839,"remaining_time":0.5016471877},
{"learn":[0.3291163181],"iteration":447,"passed_time":0.4063996397,"remaining_time":0.5007424132},
{"learn":[0.329116194],"iteration":448,"passed_time":0.4069028172,"remaining_time":0.4993395373},
{"learn":[0.329082595],"iteration":449,"passed_time":0.4077815892,"remaining_time":0.4983997201},
{"learn":[0.3289154565],"iteration":450,"passed_time":0.4089143992,"remaining_time":0.4977694128},
{"learn":[0.3288502986],"iteration":451,"passed_time":0.4097330228,"remaining_time":0.4967559656},
{"learn":[0.3288501718],"iteration":452,"passed_time":0.4102287731,"remaining_time":0.4953535075},
{"learn":[0.3288370759],"iteration":453,"passed_time":0.4110692097,"remaining_time":0.4943695782},
{"learn":[0.3288247777],"iteration":454,"passed_time":0.4118775075,"remaining_time":0.4933477837},
{"learn":[0.3288239163],"iteration":455,"passed_time":0.4123538627,"remaining_time":0.491930924},
{"learn":[0.3288022849],"iteration":456,"passed_time":0.4131955323,"remaining_time":0.4909522407},
{"learn":[0.3287938402],"iteration":457,"passed_time":0.4140663699,"remaining_time":0.4900086735},
{"learn":[0.3287838708],"iteration":458,"passed_time":0.4149192864,"remaining_time":0.4890443005},
{"learn":[0.3287795098],"iteration":459,"passed_time":0.415746104,"remaining_time":0.4880497742},
{"learn":[0.3287487339],"iteration":460,"passed_time":0.4165866524,"remaining_time":0.4870720296},
{"learn":[0.3287418853],"iteration":461,"passed_time":0.4173882232,"remaining_time":0.4860494894},
{"learn":[0.328731908],"iteration":462,"passed_time":0.4182238208,"remaining_time":0.4850673688},
{"learn":[0.3287296669],"iteration":463,"passed_time":0.4189686686,"remaining_time":0.4839810483},
{"learn":[0.3287169538],"iteration":464,"passed_time":0.4198114291,"remaining_time":0.4830088485},
{"learn":[0.3286723886],"iteration":465,"passed_time":0.4206292846,"remaining_time":0.4820086652},
{"learn":[0.3286522136],"iteration":466,"passed_time":0.4215172583,"remaining_time":0.4810892905},
{"learn":[0.3286520684],"iteration":467,"passed_time":0.422135714,"remaining_time":0.4798636749},
{"learn":[0.3285995746],"iteration":468,"passed_time":0.4230037845,"remaining_time":0.4789232614},
{"learn":[0.3285491827],"iteration":469,"passed_time":0.4239784817,"remaining_time":0.4781033943},
{"learn":[0.32843933],"iteration":470,"passed_time":0.4248529471,"remaining_time":0.4771702951},
{"learn":[0.3283767437],"iteration":471,"passed_time":0.4256946012,"remaining_time":0.4762007403},
{"learn":[0.3283184134],"iteration":472,"passed_time":0.426543486,"remaining_time":0.4752397826},
{"learn":[0.3283182298],"iteration":473,"passed_time":0.427072472,"remaining_time":0.4739243044},
{"learn":[0.3283180562],"iteration":474,"passed_time":0.4276213072,"remaining_time":0.4726340763},
{"learn":[0.3282255378],"iteration":475,"passed_time":0.4286685521,"remaining_time":0.471895633},
{"learn":[0.3281790913],"iteration":476,"passed_time":0.429535843,"remaining_time":0.4709585868},
{"learn":[0.3281774143],"iteration":477,"passed_time":0.4303030105,"remaining_time":0.4699124926},
{"learn":[0.3281772287],"iteration":478,"passed_time":0.4310293258,"remaining_time":0.4688231289},
{"learn":[0.3281770371],"iteration":479,"passed_time":0.4316069452,"remaining_time":0.4675741906},
{"learn":[0.3281768653],"iteration":480,"passed_time":0.4322830547,"remaining_time":0.4664343147},
{"learn":[0.3281671357],"iteration":481,"passed_time":0.4331809086,"remaining_time":0.4655346694},
{"learn":[0.3281669692],"iteration":482,"passed_time":0.4337369683,"remaining_time":0.4642691773},
{"learn":[0.3280850347],"iteration":483,"passed_time":0.4348020129,"remaining_time":0.4635492534},
{"learn":[0.3280849664],"iteration":484,"passed_time":0.435277913,"remaining_time":0.4622023199},
{"learn":[0.3280673786],"iteration":485,"passed_time":0.4361666933,"remaining_time":0.4612956386},
{"learn":[0.3280201489],"iteration":486,"passed_time":0.4369936038,"remaining_time":0.4603238578},
{"learn":[0.3279821051],"iteration":487,"passed_time":0.437847239,"remaining_time":0.4593807098},
{"learn":[0.3279661204],"iteration":488,"passed_time":0.4386331327,"remaining_time":0.4583671386},
{"learn":[0.3279071789],"iteration":489,"passed_time":0.4394389445,"remaining_time":0.457375228},
{"learn":[0.3278960968],"iteration":490,"passed_time":0.4402826953,"remaining_time":0.4564234051},
{"learn":[0.3278882738],"iteration":491,"passed_time":0.4413310852,"remaining_time":0.4556833156},
{"learn":[0.3278882193],"iteration":492,"passed_time":0.4418514933,"remaining_time":0.4543990002},
{"learn":[0.3278824555],"iteration":493,"passed_time":0.4429039403,"remaining_time":0.4536627405},
{"learn":[0.3278823832],"iteration":494,"passed_time":0.4434790715,"remaining_time":0.4524382447},
{"learn":[0.3278822091],"iteration":495,"passed_time":0.4439910352,"remaining_time":0.451152181},
{"learn":[0.3278676849],"iteration":496,"passed_time":0.444960037,"remaining_time":0.4503317879},
{"learn":[0.3278675639],"iteration":497,"passed_time":0.4454355736,"remaining_time":0.4490133694},
{"learn":[0.3278674496],"iteration":498,"passed_time":0.4459064371,"remaining_time":0.4476936373},
{"learn":[0.3278673416],"iteration":499,"passed_time":0.4464252578,"remaining_time":0.4464252578},
{"learn":[0.3278281347],"iteration":500,"passed_time":0.4473412616,"remaining_time":0.4455554681},
{"learn":[0.3278280887],"iteration":501,"passed_time":0.447977893,"remaining_time":0.4444083481},
{"learn":[0.3278212534],"iteration":502,"passed_time":0.4488542143,"remaining_time":0.4435000885},
{"learn":[0.3278212125],"iteration":503,"passed_time":0.4493615542,"remaining_time":0.4422288311},
{"learn":[0.3278211734],"iteration":504,"passed_time":0.4498612664,"remaining_time":0.4409531225},
{"learn":[0.3277760834],"iteration":505,"passed_time":0.4507181316,"remaining_time":0.4400291641},
{"learn":[0.3276739486],"iteration":506,"passed_time":0.4515589362,"remaining_time":0.4390898532},
{"learn":[0.3276327397],"iteration":507,"passed_time":0.4523976292,"remaining_time":0.438148885},
{"learn":[0.3276245613],"iteration":508,"passed_time":0.4534151309,"remaining_time":0.4373808041},
{"learn":[0.3275754398],"iteration":509,"passed_time":0.4542218794,"remaining_time":0.4364092567},
{"learn":[0.3275588351],"iteration":510,"passed_time":0.4550443729,"remaining_time":0.4354534215},
{"learn":[0.3275574582],"iteration":511,"passed_time":0.4558940108,"remaining_time":0.4345239791},
{"learn":[0.3275542238],"iteration":512,"passed_time":0.4568041244,"remaining_time":0.4336522584},
{"learn":[0.3275232779],"iteration":513,"passed_time":0.4576252106,"remaining_time":0.4326962108},
{"learn":[0.3275231972],"iteration":514,"passed_time":0.4581282604,"remaining_time":0.4314411773},
{"learn":[0.3275231507],"iteration":515,"passed_time":0.4586251855,"remaining_time":0.4301833135},
{"learn":[0.3274333407],"iteration":516,"passed_time":0.4595089991,"remaining_time":0.4292898386},
{"learn":[0.3274021139],"iteration":517,"passed_time":0.4603921206,"remaining_time":0.428395757},
{"learn":[0.3273582854],"iteration":518,"passed_time":0.4612050815,"remaining_time":0.427436694},
{"learn":[0.327273538],"iteration":519,"passed_time":0.4620435545,"remaining_time":0.4265017427},
{"learn":[0.3272734811],"iteration":520,"passed_time":0.4627569629,"remaining_time":0.425452179},
{"learn":[0.3270805549],"iteration":521,"passed_time":0.4636582852,"remaining_time":0.4245759777},
{"learn":[0.3270544929],"iteration":522,"passed_time":0.4644952646,"remaining_time":0.4236409966},
{"learn":[0.3270522156],"iteration":523,"passed_time":0.4653473896,"remaining_time":0.4227201478},
{"learn":[0.3270338166],"iteration":524,"passed_time":0.4661914404,"remaining_time":0.4217922556},
{"learn":[0.3270337639],"iteration":525,"passed_time":0.4667500393,"remaining_time":0.4206074498},
{"learn":[0.3270337188],"iteration":526,"passed_time":0.4673387151,"remaining_time":0.4194520156},
{"learn":[0.3270334508],"iteration":527,"passed_time":0.4679957084,"remaining_time":0.4183597999},
{"learn":[0.3269737586],"iteration":528,"passed_time":0.4689127348,"remaining_time":0.4175007526},
{"learn":[0.3269736828],"iteration":529,"passed_time":0.4695706343,"remaining_time":0.4164116945},
{"learn":[0.3269488346],"iteration":530,"passed_time":0.4706251791,"remaining_time":0.4156745932},
{"learn":[0.3269487806],"iteration":531,"passed_time":0.4711251482,"remaining_time":0.4144484386},
{"learn":[0.3269156471],"iteration":532,"passed_time":0.4721376936,"remaining_time":0.4136741143},
{"learn":[0.3269055177],"iteration":533,"passed_time":0.4729678187,"remaining_time":0.4127397069},
{"learn":[0.3269054765],"iteration":534,"passed_time":0.4736867177,"remaining_time":0.4117090163},
{"learn":[0.3269045889],"iteration":535,"passed_time":0.4744747766,"remaining_time":0.4107393589},
{"learn":[0.3268842909],"iteration":536,"passed_time":0.475394552,"remaining_time":0.4098839434},
{"learn":[0.3268391008],"iteration":537,"passed_time":0.4767428347,"remaining_time":0.4093962632},
{"learn":[0.3267959398],"iteration":538,"passed_time":0.477855056,"remaining_time":0.4087034895},
{"learn":[0.3267958728],"iteration":539,"passed_time":0.4784232122,"remaining_time":0.4075456993},
{"learn":[0.3267641501],"iteration":540,"passed_time":0.479327481,"remaining_time":0.4066752565},
{"learn":[0.3266501687],"iteration":541,"passed_time":0.4801555947,"remaining_time":0.4057403365},
{"learn":[0.3266116689],"iteration":542,"passed_time":0.481036107,"remaining_time":0.4048499096},
{"learn":[0.3266115996],"iteration":543,"passed_time":0.4815175512,"remaining_time":0.4036250062},
{"learn":[0.3266115342],"iteration":544,"passed_time":0.4820628906,"remaining_time":0.4024561747},
{"learn":[0.3266114723],"iteration":545,"passed_time":0.4825058972,"remaining_time":0.4012045372},
{"learn":[0.3265728539],"iteration":546,"passed_time":0.483393715,"remaining_time":0.4003242284},
{"learn":[0.3265714702],"iteration":547,"passed_time":0.4842114525,"remaining_time":0.3993860885},
{"learn":[0.3265517392],"iteration":548,"passed_time":0.4850721101,"remaining_time":0.398483646},
{"learn":[0.3265516946],"iteration":549,"passed_time":0.4855163905,"remaining_time":0.3972406832},
{"learn":[0.3265516525],"iteration":550,"passed_time":0.4860127091,"remaining_time":0.3960430243},
{"learn":[0.3265510831],"iteration":551,"passed_time":0.4868368429,"remaining_time":0.3951139595},
{"learn":[0.3265452009],"iteration":552,"passed_time":0.4877036269,"remaining_time":0.3942197491},
{"learn":[0.3264928271],"iteration":553,"passed_time":0.4885824684,"remaining_time":0.3933353446},
{"learn":[0.3264667499],"iteration":554,"passed_time":0.4894316885,"remaining_time":0.3924272097},
{"learn":[0.3264385692],"iteration":555,"passed_time":0.4902659479,"remaining_time":0.3915073397},
{"learn":[0.3263306488],"iteration":556,"passed_time":0.4911092827,"remaining_time":0.3905949951},
{"learn":[0.3263306076],"iteration":557,"passed_time":0.4916029172,"remaining_time":0.389405895},
{"learn":[0.3263305686],"iteration":558,"passed_time":0.4921477651,"remaining_time":0.3882596859},
{"learn":[0.3263304788],"iteration":559,"passed_time":0.4926723795,"remaining_time":0.3870997268},
{"learn":[0.326330444],"iteration":560,"passed_time":0.4939005314,"remaining_time":0.3864925727},
{"learn":[0.3262950681],"iteration":561,"passed_time":0.4953744717,"remaining_time":0.3860747662},
{"learn":[0.3262597615],"iteration":562,"passed_time":0.4967715988,"remaining_time":0.3855935856},
{"learn":[0.3262596963],"iteration":563,"passed_time":0.497545001,"remaining_time":0.3846269866},
{"learn":[0.3262596644],"iteration":564,"passed_time":0.4982985891,"remaining_time":0.3836458164},
{"learn":[0.326252641],"iteration":565,"passed_time":0.4998369734,"remaining_time":0.3832672199},
{"learn":[0.3262447984],"iteration":566,"passed_time":0.5013052831,"remaining_time":0.3828310186},
{"learn":[0.3262447618],"iteration":567,"passed_time":0.5022594957,"remaining_time":0.3820001799},
{"learn":[0.3262080581],"iteration":568,"passed_time":0.5037837236,"remaining_time":0.3816006764},
{"learn":[0.3262080248],"iteration":569,"passed_time":0.5047013843,"remaining_time":0.3807396408},
{"learn":[0.3261755674],"iteration":570,"passed_time":0.5062310838,"remaining_time":0.3803382399},
{"learn":[0.3261259852],"iteration":571,"passed_time":0.5075365789,"remaining_time":0.3797651325},
{"learn":[0.3260681473],"iteration":572,"passed_time":0.5086906994,"remaining_time":0.3790766643},
{"learn":[0.3260681157],"iteration":573,"passed_time":0.5094294155,"remaining_time":0.378078277},
{"learn":[0.3260680295],"iteration":574,"passed_time":0.5102981449,"remaining_time":0.3771768897},
{"learn":[0.3260670717],"iteration":575,"passed_time":0.5114919008,"remaining_time":0.3765148714},
{"learn":[0.3260670514],"iteration":576,"passed_time":0.5122360906,"remaining_time":0.3755214321},
{"learn":[0.3260442405],"iteration":577,"passed_time":0.5134738515,"remaining_time":0.3748892134},
{"learn":[0.325979129],"iteration":578,"passed_time":0.5144493916,"remaining_time":0.3740642381},
{"learn":[0.3259740852],"iteration":579,"passed_time":0.5161490169,"remaining_time":0.3737630812},
{"learn":[0.3259740644],"iteration":580,"passed_time":0.516896582,"remaining_time":0.3727705127},
{"learn":[0.3259679073],"iteration":581,"passed_time":0.5185620632,"remaining_time":0.3724380454},
{"learn":[0.325952273],"iteration":582,"passed_time":0.5193748251,"remaining_time":0.3714910841},
{"learn":[0.3259227435],"iteration":583,"passed_time":0.5202427698,"remaining_time":0.3705838908},
{"learn":[0.3259059058],"iteration":584,"passed_time":0.5210340908,"remaining_time":0.3696224747},
{"learn":[0.3258871837],"iteration":585,"passed_time":0.5219767174,"remaining_time":0.3687685341},
{"learn":[0.3258296713],"iteration":586,"passed_time":0.5232967883,"remaining_time":0.3681798528},
{"learn":[0.3257873009],"iteration":587,"passed_time":0.5241060836,"remaining_time":0.3672307933},
{"learn":[0.3257872605],"iteration":588,"passed_time":0.5246627891,"remaining_time":0.366105953},
{"learn":[0.3257421011],"iteration":589,"passed_time":0.5255587189,"remaining_time":0.3652187707},
{"learn":[0.3257079379],"iteration":590,"passed_time":0.5272526398,"remaining_time":0.3648838066},
{"learn":[0.3257079224],"iteration":591,"passed_time":0.5278499194,"remaining_time":0.3637884579},
{"learn":[0.3257076683],"iteration":592,"passed_time":0.5284029219,"remaining_time":0.3626644},
{"learn":[0.3257076546],"iteration":593,"passed_time":0.5289278041,"remaining_time":0.3615230446},
{"learn":[0.3256786483],"iteration":594,"passed_time":0.5299072173,"remaining_time":0.3606931479},
{"learn":[0.3256786353],"iteration":595,"passed_time":0.5303590757,"remaining_time":0.3595051453},
{"learn":[0.3256396134],"iteration":596,"passed_time":0.5312244304,"remaining_time":0.3585987361},
{"learn":[0.3256396009],"iteration":597,"passed_time":0.5316635478,"remaining_time":0.3574059301},
{"learn":[0.3256230324],"iteration":598,"passed_time":0.5325202826,"remaining_time":0.3564952142},
{"learn":[0.325582943],"iteration":599,"passed_time":0.5332857446,"remaining_time":0.3555238297},
{"learn":[0.3255829312],"iteration":600,"passed_time":0.5337746503,"remaining_time":0.3543695266},
{"learn":[0.3255511556],"iteration":601,"passed_time":0.5347107251,"remaining_time":0.3535130707},
{"learn":[0.3254487671],"iteration":602,"passed_time":0.5355275054,"remaining_time":0.3525778104},
{"learn":[0.3254487506],"iteration":603,"passed_time":0.5360194953,"remaining_time":0.3514300003},
{"learn":[0.325448727],"iteration":604,"passed_time":0.536629661,"remaining_time":0.3503615142},
{"learn":[0.3254285902],"iteration":605,"passed_time":0.5374842567,"remaining_time":0.3494534606},
{"learn":[0.3253905899],"iteration":606,"passed_time":0.5384354234,"remaining_time":0.3486081077},
{"learn":[0.3252843866],"iteration":607,"passed_time":0.5397163715,"remaining_time":0.347975029},
{"learn":[0.3252818291],"iteration":608,"passed_time":0.5405161708,"remaining_time":0.3470309077},
{"learn":[0.3252818134],"iteration":609,"passed_time":0.5410219303,"remaining_time":0.3458992669},
{"learn":[0.3252817977],"iteration":610,"passed_time":0.5414952129,"remaining_time":0.3447489981},
{"learn":[0.3252630054],"iteration":611,"passed_time":0.5423589289,"remaining_time":0.3438484713},
{"learn":[0.3252629936],"iteration":612,"passed_time":0.5428702862,"remaining_time":0.342725613},
{"learn":[0.3252466645],"iteration":613,"passed_time":0.5435096334,"remaining_time":0.3416852093},
{"learn":[0.3251460941],"iteration":614,"passed_time":0.5444191112,"remaining_time":0.340815216},
{"learn":[0.3251374466],"iteration":615,"passed_time":0.5452315536,"remaining_time":0.3398846049},
{"learn":[0.3251374362],"iteration":616,"passed_time":0.5458403714,"remaining_time":0.3388279777},
{"learn":[0.3251152504],"iteration":617,"passed_time":0.5467237375,"remaining_time":0.3379425044},
{"learn":[0.3250891744],"iteration":618,"passed_time":0.5475575181,"remaining_time":0.3370265176},
{"learn":[0.3250891629],"iteration":619,"passed_time":0.5480473273,"remaining_time":0.3358999748},
{"learn":[0.3250699767],"iteration":620,"passed_time":0.5489078585,"remaining_time":0.3350017365},
{"learn":[0.3250642668],"iteration":621,"passed_time":0.5497235212,"remaining_time":0.3340763521},
{"learn":[0.3250464303],"iteration":622,"passed_time":0.550777904,"remaining_time":0.3332957782},
{"learn":[0.3250464205],"iteration":623,"passed_time":0.5514383958,"remaining_time":0.3322769821},
{"learn":[0.3250423132],"iteration":624,"passed_time":0.5522562293,"remaining_time":0.3313537376},
{"learn":[0.3250422993],"iteration":625,"passed_time":0.5527378715,"remaining_time":0.3302299743},
{"learn":[0.3250250498],"iteration":626,"passed_time":0.553693834,"remaining_time":0.3293904307},
{"learn":[0.3248993388],"iteration":627,"passed_time":0.5545033939,"remaining_time":0.3284637939},
{"learn":[0.3248860428],"iteration":628,"passed_time":0.5553349279,"remaining_time":0.32755049},
{"learn":[0.3248860305],"iteration":629,"passed_time":0.5558241476,"remaining_time":0.3264364042},
{"learn":[0.3248860079],"iteration":630,"passed_time":0.5564447173,"remaining_time":0.3254011105},
{"learn":[0.3248859965],"iteration":631,"passed_time":0.5569588641,"remaining_time":0.3243051614},
{"learn":[0.3248859856],"iteration":632,"passed_time":0.5574495856,"remaining_time":0.3231974691},
{"learn":[0.3248500063],"iteration":633,"passed_time":0.5583307181,"remaining_time":0.3223171023},
{"learn":[0.3248499991],"iteration":634,"passed_time":0.5587836042,"remaining_time":0.3211905757},
{"learn":[0.3248499924],"iteration":635,"passed_time":0.5592899635,"remaining_time":0.3200967716},
{"learn":[0.3248199669],"iteration":636,"passed_time":0.5601649632,"remaining_time":0.3192148848},
{"learn":[0.324811551],"iteration":637,"passed_time":0.5610149116,"remaining_time":0.3183188056},
{"learn":[0.3247972525],"iteration":638,"passed_time":0.5617653951,"remaining_time":0.3173666786},
{"learn":[0.32478328],"iteration":639,"passed_time":0.5626211751,"remaining_time":0.316474411},
{"learn":[0.32477639],"iteration":640,"passed_time":0.5634672732,"remaining_time":0.3155768348},
{"learn":[0.3247763861],"iteration":641,"passed_time":0.5639779847,"remaining_time":0.3144923965},
{"learn":[0.3247763825],"iteration":642,"passed_time":0.5644842275,"remaining_time":0.3134072616},
{"learn":[0.3247677717],"iteration":643,"passed_time":0.5655908915,"remaining_time":0.3126558345},
{"learn":[0.3247517103],"iteration":644,"passed_time":0.5663850155,"remaining_time":0.3117312876},
{"learn":[0.3247517074],"iteration":645,"passed_time":0.5670712386,"remaining_time":0.3107480162},
{"learn":[0.3247517012],"iteration":646,"passed_time":0.5675793223,"remaining_time":0.309668471},
{"learn":[0.3247516923],"iteration":647,"passed_time":0.5680779956,"remaining_time":0.3085855779},
{"learn":[0.3247516897],"iteration":648,"passed_time":0.5685066834,"remaining_time":0.3074666346},
{"learn":[0.3247516873],"iteration":649,"passed_time":0.5690016495,"remaining_time":0.3063855036},
{"learn":[0.324751685],"iteration":650,"passed_time":0.569508854,"remaining_time":0.3053127343},
{"learn":[0.3247516828],"iteration":651,"passed_time":0.5699952071,"remaining_time":0.3042305707},
{"learn":[0.3247337164],"iteration":652,"passed_time":0.5708933156,"remaining_time":0.303369036},
{"learn":[0.3247337141],"iteration":653,"passed_time":0.5713937226,"remaining_time":0.3022969847},
{"learn":[0.3247266107],"iteration":654,"passed_time":0.5722869219,"remaining_time":0.3014335695},
{"learn":[0.3247191276],"iteration":655,"passed_time":0.5731466984,"remaining_time":0.300552537},
{"learn":[0.3247141831],"iteration":656,"passed_time":0.5739886056,"remaining_time":0.2996622401},
{"learn":[0.3247139016],"iteration":657,"passed_time":0.57457385,"remaining_time":0.298638688},
{"learn":[0.3247137306],"iteration":658,"passed_time":0.5753042309,"remaining_time":0.2976915671},
{"learn":[0.3247137285],"iteration":659,"passed_time":0.5757930417,"remaining_time":0.2966206579},
{"learn":[0.3247137265],"iteration":660,"passed_time":0.5763768527,"remaining_time":0.2956002316},
{"learn":[0.324689175],"iteration":661,"passed_time":0.5774099694,"remaining_time":0.2948105282},
{"learn":[0.3246891743],"iteration":662,"passed_time":0.5778950765,"remaining_time":0.2937415396},
{"learn":[0.3246891737],"iteration":663,"passed_time":0.5784016017,"remaining_time":0.2926851478},
{"learn":[0.3246787363],"iteration":664,"passed_time":0.5792840824,"remaining_time":0.2918198009},
{"learn":[0.324678732],"iteration":665,"passed_time":0.5797471901,"remaining_time":0.2907440863},
{"learn":[0.3246787278],"iteration":666,"passed_time":0.5802696536,"remaining_time":0.289699842},
{"learn":[0.3246787277],"iteration":667,"passed_time":0.5810117452,"remaining_time":0.2887663165},
{"learn":[0.3246653751],"iteration":668,"passed_time":0.5819598091,"remaining_time":0.2879352718},
{"learn":[0.3246653751],"iteration":669,"passed_time":0.5825906286,"remaining_time":0.2869476231},
{"learn":[0.324616083],"iteration":670,"passed_time":0.5835072531,"remaining_time":0.2861011718},
{"learn":[0.3246160828],"iteration":671,"passed_time":0.5839713927,"remaining_time":0.285033656},
{"learn":[0.3245744223],"iteration":672,"passed_time":0.5849352433,"remaining_time":0.2842107349},
{"learn":[0.3245061685],"iteration":673,"passed_time":0.5857810676,"remaining_time":0.2833303086},
{"learn":[0.3245061656],"iteration":674,"passed_time":0.5862789994,"remaining_time":0.2822824812},
{"learn":[0.3244970749],"iteration":675,"passed_time":0.5871008638,"remaining_time":0.2813915383},
{"learn":[0.3244664729],"iteration":676,"passed_time":0.5880112496,"remaining_time":0.2805430334},
{"learn":[0.3244661203],"iteration":677,"passed_time":0.5889710112,"remaining_time":0.2797177959},
{"learn":[0.3244660748],"iteration":678,"passed_time":0.5896341593,"remaining_time":0.2787519369},
{"learn":[0.3244660722],"iteration":679,"passed_time":0.5901263611,"remaining_time":0.2777065229},
{"learn":[0.3244563445],"iteration":680,"passed_time":0.5910732704,"remaining_time":0.2768757317},
{"learn":[0.3244563445],"iteration":681,"passed_time":0.5916090459,"remaining_time":0.2758528982},
{"learn":[0.3244401229],"iteration":682,"passed_time":0.5924709943,"remaining_time":0.2749828773},
{"learn":[0.3244172484],"iteration":683,"passed_time":0.5932702273,"remaining_time":0.2740839062},
{"learn":[0.3244172458],"iteration":684,"passed_time":0.5937902381,"remaining_time":0.2730568248},
{"learn":[0.3244172458],"iteration":685,"passed_time":0.5945141809,"remaining_time":0.2721245668},
{"learn":[0.3244040682],"iteration":686,"passed_time":0.5954390473,"remaining_time":0.2712844568},
{"learn":[0.3244040682],"iteration":687,"passed_time":0.5959370903,"remaining_time":0.2702505409},
{"learn":[0.3243777538],"iteration":688,"passed_time":0.5968490046,"remaining_time":0.2694049933},
{"learn":[0.3243777512],"iteration":689,"passed_time":0.5975040702,"remaining_time":0.2684438576},
{"learn":[0.3243553944],"iteration":690,"passed_time":0.5984216321,"remaining_time":0.2676009903},
{"learn":[0.3243189383],"iteration":691,"passed_time":0.5992747781,"remaining_time":0.2667292365},
{"learn":[0.3243189381],"iteration":692,"passed_time":0.5997663734,"remaining_time":0.2656973689},
{"learn":[0.3243161738],"iteration":693,"passed_time":0.6004046605,"remaining_time":0.2647317379},
{"learn":[0.324298748],"iteration":694,"passed_time":0.6013857148,"remaining_time":0.2639174719},
{"learn":[0.3242987473],"iteration":695,"passed_time":0.6018540735,"remaining_time":0.2628787907},
{"learn":[0.3242530373],"iteration":696,"passed_time":0.6027122295,"remaining_time":0.2620111987},
{"learn":[0.3242530352],"iteration":697,"passed_time":0.6031747759,"remaining_time":0.2609724675},
{"learn":[0.3242530319],"iteration":698,"passed_time":0.6037450279,"remaining_time":0.2599817645},
{"learn":[0.3242456926],"iteration":699,"passed_time":0.6046486359,"remaining_time":0.2591351297},
{"learn":[0.3242298649],"iteration":700,"passed_time":0.6054371423,"remaining_time":0.2582392376},
{"learn":[0.3242297873],"iteration":701,"passed_time":0.6060259212,"remaining_time":0.2572588668},
{"learn":[0.3241883516],"iteration":702,"passed_time":0.6068802515,"remaining_time":0.256391799},
{"learn":[0.3241883489],"iteration":703,"passed_time":0.607330833,"remaining_time":0.2553550093},
{"learn":[0.3241477713],"iteration":704,"passed_time":0.6083992704,"remaining_time":0.2545784181},
{"learn":[0.3241400147],"iteration":705,"passed_time":0.6091957301,"remaining_time":0.2536877403},
{"learn":[0.3241164333],"iteration":706,"passed_time":0.6107370821,"remaining_time":0.2531060326},
{"learn":[0.3240825289],"iteration":707,"passed_time":0.6121917295,"remaining_time":0.2524858545},
{"learn":[0.3240622788],"iteration":708,"passed_time":0.6130418658,"remaining_time":0.2516152087},
{"learn":[0.3240425557],"iteration":709,"passed_time":0.6151718678,"remaining_time":0.2512673826},
{"learn":[0.3240425093],"iteration":710,"passed_time":0.6159315128,"remaining_time":0.2503575347},
{"learn":[0.3239542546],"iteration":711,"passed_time":0.6175582701,"remaining_time":0.2497988508},
{"learn":[0.3239147403],"iteration":712,"passed_time":0.6183382303,"remaining_time":0.2488963143},
{"learn":[0.3238905833],"iteration":713,"passed_time":0.6193577561,"remaining_time":0.2480900816},
{"learn":[0.3238836004],"iteration":714,"passed_time":0.6201590129,"remaining_time":0.2471962499},
{"learn":[0.3238249113],"iteration":715,"passed_time":0.621551593,"remaining_time":0.246537224},
{"learn":[0.3238249039],"iteration":716,"passed_time":0.6224705332,"remaining_time":0.2456892063},
{"learn":[0.3238029785],"iteration":717,"passed_time":0.6241471792,"remaining_time":0.2451385857},
{"learn":[0.3237858886],"iteration":718,"passed_time":0.6254716567,"remaining_time":0.2444471982},
{"learn":[0.3237790476],"iteration":719,"passed_time":0.6273164493,"remaining_time":0.2439563969},
{"learn":[0.3237450453],"iteration":720,"passed_time":0.6295517231,"remaining_time":0.2436129414},
{"learn":[0.3237422784],"iteration":721,"passed_time":0.6306604645,"remaining_time":0.2428304835},
{"learn":[0.3237422721],"iteration":722,"passed_time":0.6315891946,"remaining_time":0.2419781562},
{"learn":[0.3237181059],"iteration":723,"passed_time":0.633124114,"remaining_time":0.2413567064},
{"learn":[0.3237180513],"iteration":724,"passed_time":0.6343458321,"remaining_time":0.2406139363},
{"learn":[0.3236988132],"iteration":725,"passed_time":0.635807961,"remaining_time":0.2399605803},
{"learn":[0.323698809],"iteration":726,"passed_time":0.6365053944,"remaining_time":0.2390178441},
{"learn":[0.3236988084],"iteration":727,"passed_time":0.6376882926,"remaining_time":0.2382571643},
{"learn":[0.3236988045],"iteration":728,"passed_time":0.6387455378,"remaining_time":0.2374486155},
{"learn":[0.3236861834],"iteration":729,"passed_time":0.6402720667,"remaining_time":0.2368129562},
{"learn":[0.3236861798],"iteration":730,"passed_time":0.641385455,"remaining_time":0.2360228282},
{"learn":[0.3236861767],"iteration":731,"passed_time":0.6422841298,"remaining_time":0.235153206},
{"learn":[0.3236653958],"iteration":732,"passed_time":0.6437617272,"remaining_time":0.2344943808},
{"learn":[0.3236639954],"iteration":733,"passed_time":0.6449025893,"remaining_time":0.2337112926},
{"learn":[0.3236432129],"iteration":734,"passed_time":0.6465858091,"remaining_time":0.2331227747},
{"learn":[0.3236432096],"iteration":735,"passed_time":0.647399518,"remaining_time":0.2322193923},
{"learn":[0.3236314165],"iteration":736,"passed_time":0.6482433154,"remaining_time":0.2313269904},
{"learn":[0.3236141593],"iteration":737,"passed_time":0.6490257074,"remaining_time":0.2304129205},
{"learn":[0.323614157],"iteration":738,"passed_time":0.6499033932,"remaining_time":0.2295328628},
{"learn":[0.323614151],"iteration":739,"passed_time":0.6511233719,"remaining_time":0.2287730766},
{"learn":[0.3236140291],"iteration":740,"passed_time":0.6523810491,"remaining_time":0.228025225},
{"learn":[0.3235882543],"iteration":741,"passed_time":0.6542241906,"remaining_time":0.2274795703},
{"learn":[0.3235882098],"iteration":742,"passed_time":0.6554236211,"remaining_time":0.2267077667},
{"learn":[0.3235882095],"iteration":743,"passed_time":0.6561258504,"remaining_time":0.2257637335},
{"learn":[0.3235882072],"iteration":744,"passed_time":0.6570416447,"remaining_time":0.2248934489},
{"learn":[0.3235881647],"iteration":745,"passed_time":0.6577786206,"remaining_time":0.2239621577},
{"learn":[0.323581462],"iteration":746,"passed_time":0.6595040231,"remaining_time":0.2233661551},
{"learn":[0.3235814215],"iteration":747,"passed_time":0.6599836612,"remaining_time":0.2223474367},
{"learn":[0.3235809862],"iteration":748,"passed_time":0.6612897485,"remaining_time":0.221607112},
{"learn":[0.3235809449],"iteration":749,"passed_time":0.6620782627,"remaining_time":0.2206927542},
{"learn":[0.3234807887],"iteration":750,"passed_time":0.6631901939,"remaining_time":0.2198859631},
{"learn":[0.3234807506],"iteration":751,"passed_time":0.6643975473,"remaining_time":0.2191098294},
{"learn":[0.3234804314],"iteration":752,"passed_time":0.6651414064,"remaining_time":0.2181805145},
{"learn":[0.3234649497],"iteration":753,"passed_time":0.6665012497,"remaining_time":0.2174526624},
{"learn":[0.3234649278],"iteration":754,"passed_time":0.6674768102,"remaining_time":0.2165984351},
{"learn":[0.3234460587],"iteration":755,"passed_time":0.6686036968,"remaining_time":0.2157927275},
{"learn":[0.3234163454],"iteration":756,"passed_time":0.6694400528,"remaining_time":0.2148929099},
{"learn":[0.323416184],"iteration":757,"passed_time":0.6702366842,"remaining_time":0.2139805773},
{"learn":[0.3233713103],"iteration":758,"passed_time":0.6711292809,"remaining_time":0.2130990207},
{"learn":[0.3233713094],"iteration":759,"passed_time":0.6716007601,"remaining_time":0.2120844506},
{"learn":[0.3233708331],"iteration":760,"passed_time":0.6724407373,"remaining_time":0.2111870384},
{"learn":[0.3233583496],"iteration":761,"passed_time":0.6732848229,"remaining_time":0.2102910602},
{"learn":[0.3233571521],"iteration":762,"passed_time":0.6739814909,"remaining_time":0.2093494277},
{"learn":[0.323341742],"iteration":763,"passed_time":0.6748221745,"remaining_time":0.208452923},
{"learn":[0.323320943],"iteration":764,"passed_time":0.675684575,"remaining_time":0.2075632355},
{"learn":[0.3233209207],"iteration":765,"passed_time":0.6762719662,"remaining_time":0.2065896085},
{"learn":[0.3233148124],"iteration":766,"passed_time":0.6770554639,"remaining_time":0.205676562},
{"learn":[0.323297177],"iteration":767,"passed_time":0.6778726647,"remaining_time":0.2047740341},
{"learn":[0.3232971209],"iteration":768,"passed_time":0.6784741344,"remaining_time":0.2038069246},
{"learn":[0.3232970942],"iteration":769,"passed_time":0.6789600779,"remaining_time":0.202806257},
{"learn":[0.3232475037],"iteration":770,"passed_time":0.6805010931,"remaining_time":0.2021202987},
{"learn":[0.3232474986],"iteration":771,"passed_time":0.6809705686,"remaining_time":0.2011156602},
{"learn":[0.3232251494],"iteration":772,"passed_time":0.6818685251,"remaining_time":0.2002382344},
{"learn":[0.3232055058],"iteration":773,"passed_time":0.682645501,"remaining_time":0.1993254305},
{"learn":[0.3231877291],"iteration":774,"passed_time":0.6834223366,"remaining_time":0.1984129364},
{"learn":[0.3231778446],"iteration":775,"passed_time":0.6842229012,"remaining_time":0.1975076416},
{"learn":[0.3231778084],"iteration":776,"passed_time":0.6848382454,"remaining_time":0.1965494578},
{"learn":[0.3231778042],"iteration":777,"passed_time":0.6852953733,"remaining_time":0.1955470088},
{"learn":[0.32316924],"iteration":778,"passed_time":0.6861972546,"remaining_time":0.1946721351},
{"learn":[0.3231673629],"iteration":779,"passed_time":0.6869879345,"remaining_time":0.1937658277},
{"learn":[0.3231347534],"iteration":780,"passed_time":0.6877822035,"remaining_time":0.1928608227},
{"learn":[0.3231209663],"iteration":781,"passed_time":0.6885835636,"remaining_time":0.1919580778},
{"learn":[0.3231209425],"iteration":782,"passed_time":0.6891087089,"remaining_time":0.1909790419},
{"learn":[0.3231139787],"iteration":783,"passed_time":0.6899472125,"remaining_time":0.1900874973},
{"learn":[0.323107735],"iteration":784,"passed_time":0.6907452956,"remaining_time":0.1891850173},
{"learn":[0.323094563],"iteration":785,"passed_time":0.6915413738,"remaining_time":0.188282257},
{"learn":[0.3230901901],"iteration":786,"passed_time":0.6923303432,"remaining_time":0.1873778438},
{"learn":[0.3230721893],"iteration":787,"passed_time":0.6931210037,"remaining_time":0.1864741787},
{"learn":[0.3230721833],"iteration":788,"passed_time":0.6935676412,"remaining_time":0.1854787988},
{"learn":[0.3228914672],"iteration":789,"passed_time":0.6946689342,"remaining_time":0.1846588306},
{"learn":[0.3228914427],"iteration":790,"passed_time":0.6951762829,"remaining_time":0.1836812176},
{"learn":[0.3228914393],"iteration":791,"passed_time":0.6957014205,"remaining_time":0.182709464},
{"learn":[0.3228738316],"iteration":792,"passed_time":0.6965605089,"remaining_time":0.1818260093},
{"learn":[0.3228437887],"iteration":793,"passed_time":0.6973822683,"remaining_time":0.1809329311},
{"learn":[0.3228437741],"iteration":794,"passed_time":0.6978155259,"remaining_time":0.1799398526},
{"learn":[0.3228437712],"iteration":795,"passed_time":0.6986501745,"remaining_time":0.1790510497},
{"learn":[0.3228437685],"iteration":796,"passed_time":0.699112234,"remaining_time":0.1780674824},
{"learn":[0.3226994982],"iteration":797,"passed_time":0.6999885584,"remaining_time":0.1771900862},
{"learn":[0.3226865057],"iteration":798,"passed_time":0.7008625126,"remaining_time":0.1763120964},
{"learn":[0.3226864969],"iteration":799,"passed_time":0.7018726157,"remaining_time":0.1754681539},
{"learn":[0.3226653283],"iteration":800,"passed_time":0.7026991023,"remaining_time":0.174578179},
{"learn":[0.3226410765],"iteration":801,"passed_time":0.7035153838,"remaining_time":0.1736858429},
{"learn":[0.3226384581],"iteration":802,"passed_time":0.7043413361,"remaining_time":0.1727960688},
{"learn":[0.3225645611],"iteration":803,"passed_time":0.7053674199,"remaining_time":0.1719552417},
{"learn":[0.322533653],"iteration":804,"passed_time":0.7064428474,"remaining_time":0.1711259071},
{"learn":[0.3225025654],"iteration":805,"passed_time":0.7072121489,"remaining_time":0.170222279},
{"learn":[0.3224826909],"iteration":806,"passed_time":0.7080016467,"remaining_time":0.1693238139},
{"learn":[0.3224824915],"iteration":807,"passed_time":0.7085273946,"remaining_time":0.1683629453},
{"learn":[0.3224824315],"iteration":808,"passed_time":0.7091638617,"remaining_time":0.1674292924},
{"learn":[0.3224824249],"iteration":809,"passed_time":0.7096445198,"remaining_time":0.1664598256},
{"learn":[0.3224574593],"iteration":810,"passed_time":0.7105508767,"remaining_time":0.1655907715},
{"learn":[0.3224530936],"iteration":811,"passed_time":0.7114569401,"remaining_time":0.1647215576},
{"learn":[0.3224411308],"iteration":812,"passed_time":0.7122951042,"remaining_time":0.1638366353},
{"learn":[0.3224411119],"iteration":813,"passed_time":0.7128117488,"remaining_time":0.1628783603},
{"learn":[0.3224271041],"iteration":814,"passed_time":0.7136107334,"remaining_time":0.1619852585},
{"learn":[0.3224227854],"iteration":815,"passed_time":0.7144626781,"remaining_time":0.1611043294},
{"learn":[0.3224227798],"iteration":816,"passed_time":0.714908237,"remaining_time":0.1601324448},
{"learn":[0.3224227745],"iteration":817,"passed_time":0.7153933618,"remaining_time":0.1591706502},
{"learn":[0.3223691672],"iteration":818,"passed_time":0.7162344454,"remaining_time":0.158288687},
{"learn":[0.3223642419],"iteration":819,"passed_time":0.7170724756,"remaining_time":0.1574061532},
{"learn":[0.3223373501],"iteration":820,"passed_time":0.717976153,"remaining_time":0.1565380407},
{"learn":[0.3222982697],"iteration":821,"passed_time":0.7189709378,"remaining_time":0.1556895705},
{"learn":[0.3222982651],"iteration":822,"passed_time":0.7194156441,"remaining_time":0.1547224411},
{"learn":[0.3222810472],"iteration":823,"passed_time":0.7202586619,"remaining_time":0.1538416559},
{"learn":[0.3222810429],"iteration":824,"passed_time":0.72069689,"remaining_time":0.1528750979},
{"learn":[0.3222810388],"iteration":825,"passed_time":0.7212188284,"remaining_time":0.151927453},
{"learn":[0.3222778921],"iteration":826,"passed_time":0.7222486399,"remaining_time":0.1510870794},
{"learn":[0.3222778888],"iteration":827,"passed_time":0.7227548445,"remaining_time":0.1501374798},
{"learn":[0.3222744058],"iteration":828,"passed_time":0.7236042911,"remaining_time":0.1492597512},
{"learn":[0.3222744035],"iteration":829,"passed_time":0.7241331521,"remaining_time":0.1483164287},
{"learn":[0.3222729207],"iteration":830,"passed_time":0.7251688526,"remaining_time":0.1474771794},
{"learn":[0.3222701568],"iteration":831,"passed_time":0.7259754981,"remaining_time":0.1465912064},
{"learn":[0.3222396736],"iteration":832,"passed_time":0.7267915779,"remaining_time":0.1457073151},
{"learn":[0.3222355355],"iteration":833,"passed_time":0.7275733632,"remaining_time":0.1448167605},
{"learn":[0.3222354037],"iteration":834,"passed_time":0.7281710346,"remaining_time":0.1438900847},
{"learn":[0.3222353992],"iteration":835,"passed_time":0.7288789671,"remaining_time":0.1429858261},
{"learn":[0.3222306237],"iteration":836,"passed_time":0.7297346569,"remaining_time":0.1421108113},
{"learn":[0.3222306176],"iteration":837,"passed_time":0.7302023968,"remaining_time":0.1411608452},
{"learn":[0.3222058576],"iteration":838,"passed_time":0.7310636026,"remaining_time":0.1402875328},
{"learn":[0.3222058516],"iteration":839,"passed_time":0.7316838206,"remaining_time":0.1393683468},
{"learn":[0.3222056754],"iteration":840,"passed_time":0.7325235782,"remaining_time":0.138491378},
{"learn":[0.3222056701],"iteration":841,"passed_time":0.7332637028,"remaining_time":0.1375958017},
{"learn":[0.3221536505],"iteration":842,"passed_time":0.7346020763,"remaining_time":0.1368120118},
{"learn":[0.3221535857],"iteration":843,"passed_time":0.7352514426,"remaining_time":0.1358995557},
{"learn":[0.3221535791],"iteration":844,"passed_time":0.7357817591,"remaining_time":0.1349658848},
{"learn":[0.3221402383],"iteration":845,"passed_time":0.7366376907,"remaining_time":0.1340924402},
{"learn":[0.3221191268],"iteration":846,"passed_time":0.7375874509,"remaining_time":0.1332359858},
{"learn":[0.3220885666],"iteration":847,"passed_time":0.7384077,"remaining_time":0.1323560972},
{"learn":[0.3220885619],"iteration":848,"passed_time":0.7388885433,"remaining_time":0.1314159836},
{"learn":[0.3220639534],"iteration":849,"passed_time":0.7397266391,"remaining_time":0.1305399951},
{"learn":[0.3220607947],"iteration":850,"passed_time":0.7405312682,"remaining_time":0.1296582361},
{"learn":[0.3220471651],"iteration":851,"passed_time":0.7416452849,"remaining_time":0.1288304016},
{"learn":[0.3220393375],"iteration":852,"passed_time":0.7424184741,"remaining_time":0.1279431603},
{"learn":[0.3220393286],"iteration":853,"passed_time":0.7428576918,"remaining_time":0.1269990902},
{"learn":[0.3220392949],"iteration":854,"passed_time":0.7435267206,"remaining_time":0.1260951748},
{"learn":[0.3219827079],"iteration":855,"passed_time":0.7443586491,"remaining_time":0.125219212},
{"learn":[0.3219827034],"iteration":856,"passed_time":0.7448378509,"remaining_time":0.1242844955},
{"learn":[0.3219816858],"iteration":857,"passed_time":0.7455633141,"remaining_time":0.1233915974},
{"learn":[0.3219558265],"iteration":858,"passed_time":0.7464731583,"remaining_time":0.1225293543},
{"learn":[0.3219422317],"iteration":859,"passed_time":0.7472775421,"remaining_time":0.1216498324},
{"learn":[0.3218298317],"iteration":860,"passed_time":0.7481227491,"remaining_time":0.1207770756},
{"learn":[0.321816384],"iteration":861,"passed_time":0.7488999256,"remaining_time":0.1198934916},
{"learn":[0.3218137297],"iteration":862,"passed_time":0.7496908732,"remaining_time":0.1190123402},
{"learn":[0.3218137246],"iteration":863,"passed_time":0.7501943053,"remaining_time":0.1180861407},
{"learn":[0.3217974317],"iteration":864,"passed_time":0.7510886002,"remaining_time":0.1172219203},
{"learn":[0.3217524812],"iteration":865,"passed_time":0.7518803818,"remaining_time":0.1163417681},
{"learn":[0.3217524712],"iteration":866,"passed_time":0.7524062716,"remaining_time":0.1154210313},
{"learn":[0.321752467],"iteration":867,"passed_time":0.7531640333,"remaining_time":0.1145364659},
{"learn":[0.3217332214],"iteration":868,"passed_time":0.7542125787,"remaining_time":0.1136960274},
{"learn":[0.3217198617],"iteration":869,"passed_time":0.7550095751,"remaining_time":0.1128175227},
{"learn":[0.3217198578],"iteration":870,"passed_time":0.7554557835,"remaining_time":0.1118872515},
{"learn":[0.3217088176],"iteration":871,"passed_time":0.756309833,"remaining_time":0.1110179571},
{"learn":[0.3217088121],"iteration":872,"passed_time":0.7568252671,"remaining_time":0.1100994375},
{"learn":[0.3217088086],"iteration":873,"passed_time":0.7573360519,"remaining_time":0.1091811699},
{"learn":[0.321684517],"iteration":874,"passed_time":0.7581571562,"remaining_time":0.1083081652},
{"learn":[0.3216812515],"iteration":875,"passed_time":0.7590531222,"remaining_time":0.1074458757},
{"learn":[0.3216606358],"iteration":876,"passed_time":0.759854757,"remaining_time":0.1065702795},
{"learn":[0.3216486358],"iteration":877,"passed_time":0.7606298064,"remaining_time":0.1056911576},
{"learn":[0.3216486316],"iteration":878,"passed_time":0.7611336012,"remaining_time":0.1047749326},
{"learn":[0.3215894571],"iteration":879,"passed_time":0.7619172346,"remaining_time":0.1038978047},
{"learn":[0.3215894554],"iteration":880,"passed_time":0.7624129156,"remaining_time":0.1029819943},
{"learn":[0.3215713815],"iteration":881,"passed_time":0.7632692091,"remaining_time":0.1021153817},
{"learn":[0.3215713526],"iteration":882,"passed_time":0.7639488819,"remaining_time":0.1012253898},
{"learn":[0.3215713232],"iteration":883,"passed_time":0.7646345456,"remaining_time":0.1003366598},
{"learn":[0.3215713014],"iteration":884,"passed_time":0.7651883166,"remaining_time":0.09943125018},
{"learn":[0.3215134598],"iteration":885,"passed_time":0.7660531464,"remaining_time":0.09856665766},
{"learn":[0.3215134569],"iteration":886,"passed_time":0.7665220293,"remaining_time":0.09765162268},
{"learn":[0.3215134424],"iteration":887,"passed_time":0.7670015556,"remaining_time":0.09673893494},
{"learn":[0.3215121138],"iteration":888,"passed_time":0.7678146098,"remaining_time":0.09586886579},
{"learn":[0.3215046614],"iteration":889,"passed_time":0.7686533869,"remaining_time":0.09500210399},
{"learn":[0.3215046599],"iteration":890,"passed_time":0.7691224843,"remaining_time":0.09409018046},
{"learn":[0.3214930623],"iteration":891,"passed_time":0.7699663998,"remaining_time":0.09322463136},
{"learn":[0.3214328533],"iteration":892,"passed_time":0.7707484385,"remaining_time":0.09235171659},
{"learn":[0.3214297523],"iteration":893,"passed_time":0.7715221701,"remaining_time":0.09147802017},
{"learn":[0.3214217798],"iteration":894,"passed_time":0.7722779212,"remaining_time":0.09060243769},
{"learn":[0.3214042849],"iteration":895,"passed_time":0.7730990063,"remaining_time":0.08973470609},
{"learn":[0.3213886088],"iteration":896,"passed_time":0.7739027382,"remaining_time":0.08886508588},
{"learn":[0.3213886072],"iteration":897,"passed_time":0.7743626914,"remaining_time":0.08795656406},
{"learn":[0.3213886049],"iteration":898,"passed_time":0.7749429229,"remaining_time":0.08706255307},
{"learn":[0.3213883148],"iteration":899,"passed_time":0.7756469008,"remaining_time":0.08618298898},
{"learn":[0.321383333],"iteration":900,"passed_time":0.7764854881,"remaining_time":0.08531860524},
{"learn":[0.3213316119],"iteration":901,"passed_time":0.7772894112,"remaining_time":0.08445051253},
{"learn":[0.3213316012],"iteration":902,"passed_time":0.7778068574,"remaining_time":0.08355178867},
{"learn":[0.3212654539],"iteration":903,"passed_time":0.7788001948,"remaining_time":0.08270444547},
{"learn":[0.3212654535],"iteration":904,"passed_time":0.7793104245,"remaining_time":0.08180606666},
{"learn":[0.3212625642],"iteration":905,"passed_time":0.7801683594,"remaining_time":0.08094462007},
{"learn":[0.3212625518],"iteration":906,"passed_time":0.7806153842,"remaining_time":0.08004104821},
{"learn":[0.3212584129],"iteration":907,"passed_time":0.7814249121,"remaining_time":0.07917521136},
{"learn":[0.3212583917],"iteration":908,"passed_time":0.782103612,"remaining_time":0.0782964012},
{"learn":[0.3212582207],"iteration":909,"passed_time":0.7830906838,"remaining_time":0.07744852917},
{"learn":[0.321251013],"iteration":910,"passed_time":0.7838441859,"remaining_time":0.07657753298},
{"learn":[0.3212510125],"iteration":911,"passed_time":0.7843653462,"remaining_time":0.07568437551},
{"learn":[0.3211889401],"iteration":912,"passed_time":0.7852872225,"remaining_time":0.07483021726},
{"learn":[0.3211889294],"iteration":913,"passed_time":0.7858037583,"remaining_time":0.07393777157},
{"learn":[0.321183741],"iteration":914,"passed_time":0.7867015949,"remaining_time":0.07308156892},
{"learn":[0.3211837309],"iteration":915,"passed_time":0.7871434828,"remaining_time":0.07218346349},
{"learn":[0.3211837158],"iteration":916,"passed_time":0.7882190985,"remaining_time":0.07134371338},
{"learn":[0.3211837015],"iteration":917,"passed_time":0.7888911324,"remaining_time":0.07046739962},
{"learn":[0.3211796342],"iteration":918,"passed_time":0.7897875721,"remaining_time":0.0696113094},
{"learn":[0.3211796285],"iteration":919,"passed_time":0.7902970399,"remaining_time":0.06872148173},
{"learn":[0.321164151],"iteration":920,"passed_time":0.7911276179,"remaining_time":0.06786002368},
{"learn":[0.3211378419],"iteration":921,"passed_time":0.7918939389,"remaining_time":0.06699319657},
{"learn":[0.3211261049],"iteration":922,"passed_time":0.792668706,"remaining_time":0.06612729183},
{"learn":[0.3210503886],"iteration":923,"passed_time":0.7934680146,"remaining_time":0.06526360293},
{"learn":[0.3210503875],"iteration":924,"passed_time":0.793987081,"remaining_time":0.06437733089},
{"learn":[0.3210021364],"iteration":925,"passed_time":0.7948048084,"remaining_time":0.06351571903},
{"learn":[0.3209169543],"iteration":926,"passed_time":0.7956091251,"remaining_time":0.06265314577},
{"learn":[0.3209134749],"iteration":927,"passed_time":0.7966021801,"remaining_time":0.06180534156},
{"learn":[0.3209134739],"iteration":928,"passed_time":0.7971440745,"remaining_time":0.06092274412},
{"learn":[0.320905197],"iteration":929,"passed_time":0.7979826247,"remaining_time":0.06006320831},
{"learn":[0.320905197],"iteration":930,"passed_time":0.7984838479,"remaining_time":0.05917871698},
{"learn":[0.3209041885],"iteration":931,"passed_time":0.8002884947,"remaining_time":0.05839014768},
{"learn":[0.3209041884],"iteration":932,"passed_time":0.8012190801,"remaining_time":0.05753663276},
{"learn":[0.3209028723],"iteration":933,"passed_time":0.8023361987,"remaining_time":0.05669613395},
{"learn":[0.3208934759],"iteration":934,"passed_time":0.8032414871,"remaining_time":0.05584031728},
{"learn":[0.3208934449],"iteration":935,"passed_time":0.8040700969,"remaining_time":0.05497915192},
{"learn":[0.3208706497],"iteration":936,"passed_time":0.8052205402,"remaining_time":0.05413969481},
{"learn":[0.3208682949],"iteration":937,"passed_time":0.8063315333,"remaining_time":0.05329696702},
{"learn":[0.3208385952],"iteration":938,"passed_time":0.8081896892,"remaining_time":0.05250220558},
{"learn":[0.3208385815],"iteration":939,"passed_time":0.8092697709,"remaining_time":0.05165551729},
{"learn":[0.3208306642],"iteration":940,"passed_time":0.8110301033,"remaining_time":0.05085098416},
{"learn":[0.320829391],"iteration":941,"passed_time":0.8127613929,"remaining_time":0.05004263354},
{"learn":[0.3208194096],"iteration":942,"passed_time":0.8139815637,"remaining_time":0.04920143068},
{"learn":[0.3208047108],"iteration":943,"passed_time":0.8157748054,"remaining_time":0.04839342066},
{"learn":[0.3208046269],"iteration":944,"passed_time":0.8168738224,"remaining_time":0.04754292088},
{"learn":[0.3208046244],"iteration":945,"passed_time":0.8176401172,"remaining_time":0.0466729031},
{"learn":[0.3208011713],"iteration":946,"passed_time":0.8187313066,"remaining_time":0.04582128749},
{"learn":[0.3208011696],"iteration":947,"passed_time":0.8193376717,"remaining_time":0.04494257271},
{"learn":[0.3207925848],"iteration":948,"passed_time":0.8202264432,"remaining_time":0.04407960864},
{"learn":[0.3207831306],"iteration":949,"passed_time":0.821034754,"remaining_time":0.04321235547},
{"learn":[0.320772431],"iteration":950,"passed_time":0.8218170234,"remaining_time":0.04234388449},
{"learn":[0.3207724179],"iteration":951,"passed_time":0.822492474,"remaining_time":0.04147020877},
{"learn":[0.3207395802],"iteration":952,"passed_time":0.8233036642,"remaining_time":0.04060364346},
{"learn":[0.3207395721],"iteration":953,"passed_time":0.8238976613,"remaining_time":0.03972672161},
{"learn":[0.320739572],"iteration":954,"passed_time":0.8243675731,"remaining_time":0.03884454533},
{"learn":[0.3207273751],"iteration":955,"passed_time":0.8256381596,"remaining_time":0.03800008266},
{"learn":[0.3207246674],"iteration":956,"passed_time":0.8274580117,"remaining_time":0.03717940909},
{"learn":[0.3207246611],"iteration":957,"passed_time":0.8296064524,"remaining_time":0.03637105533},
{"learn":[0.3207061217],"iteration":958,"passed_time":0.8304763268,"remaining_time":0.03550524442},
{"learn":[0.320646849],"iteration":959,"passed_time":0.8312799163,"remaining_time":0.03463666318},
{"learn":[0.3206295269],"iteration":960,"passed_time":0.8321060128,"remaining_time":0.03376913059},
{"learn":[0.3205873184],"iteration":961,"passed_time":0.8328787407,"remaining_time":0.03289957604},
{"learn":[0.3205871797],"iteration":962,"passed_time":0.8336764052,"remaining_time":0.03203118068},
{"learn":[0.3205829051],"iteration":963,"passed_time":0.8347146422,"remaining_time":0.0311719161},
{"learn":[0.3205828987],"iteration":964,"passed_time":0.8352238971,"remaining_time":0.03029309471},
{"learn":[0.3205569677],"iteration":965,"passed_time":0.8360408028,"remaining_time":0.02942586676},
{"learn":[0.3205256914],"iteration":966,"passed_time":0.8368067111,"remaining_time":0.02855700255},
{"learn":[0.3205256913],"iteration":967,"passed_time":0.8372655881,"remaining_time":0.02767820126},
{"learn":[0.3205256892],"iteration":968,"passed_time":0.8378101104,"remaining_time":0.02680300663},
{"learn":[0.3205171468],"iteration":969,"passed_time":0.838717299,"remaining_time":0.02593971028},
{"learn":[0.3204705066],"iteration":970,"passed_time":0.839551791,"remaining_time":0.02507415236},
{"learn":[0.320437326],"iteration":971,"passed_time":0.8405856457,"remaining_time":0.02421440132},
{"learn":[0.320437326],"iteration":972,"passed_time":0.841022146,"remaining_time":0.02333771628},
{"learn":[0.3204252317],"iteration":973,"passed_time":0.8418934245,"remaining_time":0.02247354111},
{"learn":[0.3204240737],"iteration":974,"passed_time":0.8425458585,"remaining_time":0.02160373996},
{"learn":[0.3204175527],"iteration":975,"passed_time":0.8433249191,"remaining_time":0.02073749801},
{"learn":[0.3204023994],"iteration":976,"passed_time":0.8440894957,"remaining_time":0.01987109355},
{"learn":[0.3203793739],"iteration":977,"passed_time":0.8448448325,"remaining_time":0.01900468948},
{"learn":[0.3203662154],"iteration":978,"passed_time":0.8456497822,"remaining_time":0.01813957653},
{"learn":[0.3203661982],"iteration":979,"passed_time":0.846238276,"remaining_time":0.0172701689},
{"learn":[0.3203661972],"iteration":980,"passed_time":0.8467744557,"remaining_time":0.01640032075},
{"learn":[0.3203401361],"iteration":981,"passed_time":0.8478390624,"remaining_time":0.01554083821},
{"learn":[0.3202991119],"iteration":982,"passed_time":0.8486419471,"remaining_time":0.01467641211},
{"learn":[0.320299111],"iteration":983,"passed_time":0.8490922011,"remaining_time":0.01380637725},
{"learn":[0.3202991098],"iteration":984,"passed_time":0.849675124,"remaining_time":0.01293921509},
{"learn":[0.3202989586],"iteration":985,"passed_time":0.8503687599,"remaining_time":0.01207420146},
{"learn":[0.3202794132],"iteration":986,"passed_time":0.8511892973,"remaining_time":0.01121120655},
{"learn":[0.3202782869],"iteration":987,"passed_time":0.8519370522,"remaining_time":0.01034741359},
{"learn":[0.3202782736],"iteration":988,"passed_time":0.8527323219,"remaining_time":0.009484383762},
{"learn":[0.3202667704],"iteration":989,"passed_time":0.8535768029,"remaining_time":0.008621987908},
{"learn":[0.3202667702],"iteration":990,"passed_time":0.8540254772,"remaining_time":0.007756033597},
{"learn":[0.320264985],"iteration":991,"passed_time":0.8548794025,"remaining_time":0.00689418873},
{"learn":[0.3202647147],"iteration":992,"passed_time":0.8557226868,"remaining_time":0.006032284801},
{"learn":[0.3202621382],"iteration":993,"passed_time":0.8563002128,"remaining_time":0.005168814162},
{"learn":[0.3202309127],"iteration":994,"passed_time":0.8570699032,"remaining_time":0.004306883936},
{"learn":[0.3202282154],"iteration":995,"passed_time":0.8579278327,"remaining_time":0.003445493304},
{"learn":[0.32022811],"iteration":996,"passed_time":0.8584368013,"remaining_time":0.002583059583},
{"learn":[0.3201139493],"iteration":997,"passed_time":0.859365258,"remaining_time":0.001722174866},
{"learn":[0.3201091544],"iteration":998,"passed_time":0.8601229465,"remaining_time":0.0008609839304},
{"learn":[0.3201063873],"iteration":999,"passed_time":0.860918107,"remaining_time":0}
]}